[
  {
    "bdc": "TSLX",
    "entity": "Artisan Bidco, Inc",
    "company": "Artisan Bidco, Inc",
    "desc": null,
    "sector": "Business Services",
    "type": "First Lien",
    "affil": "",
    "fv": 37666.0,
    "cost": 37835.0,
    "par": null,
    "mark": 99.55,
    "spread": 7.0,
    "rate": 10.65,
    "baseRate": "SOFR",
    "maturity": "2029-11",
    "acq": null,
    "ccy": "USD",
    "pik": false
  },
  {
    "bdc": "TSLX",
    "entity": "Artisan Bidco, Inc",
    "company": "Artisan Bidco, Inc",
    "desc": null,
    "sector": "Business Services",
    "type": "First Lien",
    "affil": "",
    "fv": 17033.0,
    "cost": 18383.0,
    "par": null,
    "mark": 92.66,
    "spread": 7.0,
    "rate": 9.03,
    "baseRate": "EURIBOR",
    "maturity": "2029-11",
    "acq": null,
    "ccy": "EUR",
    "pik": false
  },
  {
    "bdc": "TSLX",
    "entity": "Artisan Bidco, Inc",
    "company": "Artisan Bidco, Inc",
    "desc": null,
    "sector": "Business Services",
    "type": "First Lien",
    "affil": "",
    "fv": 4187.0,
    "cost": 4219.0,
    "par": null,
    "mark": 99.24,
    "spread": 7.0,
    "rate": 10.66,
    "baseRate": "SOFR",
    "maturity": "2029-11",
    "acq": null,
    "ccy": "USD",
    "pik": false
  },
  {
    "bdc": "TSLX",
    "entity": "Azurite Intermediate Holdings, Inc",
    "company": "Azurite Intermediate Holdings, Inc",
    "desc": null,
    "sector": "Business Services",
    "type": "First Lien",
    "affil": "",
    "fv": 42037.0,
    "cost": 42165.0,
    "par": null,
    "mark": 99.7,
    "spread": 6.0,
    "rate": 9.67,
    "baseRate": "SOFR",
    "maturity": "2031-03",
    "acq": null,
    "ccy": "USD",
    "pik": false
  },
  {
    "bdc": "TSLX",
    "entity": "BCTO Ignition Purchaser, Inc",
    "company": "BCTO Ignition Purchaser, Inc",
    "desc": null,
    "sector": "Business Services",
    "type": "First Lien",
    "affil": "",
    "fv": 56157.0,
    "cost": 55135.0,
    "par": null,
    "mark": 101.85,
    "spread": 7.5,
    "rate": 11.17,
    "baseRate": "SOFR",
    "maturity": "2030-10",
    "acq": null,
    "ccy": "USD",
    "pik": true
  },
  {
    "bdc": "TSLX",
    "entity": "Crewline Buyer, Inc",
    "company": "Crewline Buyer, Inc",
    "desc": null,
    "sector": "Business Services",
    "type": "First Lien",
    "affil": "",
    "fv": 57099.0,
    "cost": 57196.0,
    "par": null,
    "mark": 99.83,
    "spread": 6.75,
    "rate": 10.42,
    "baseRate": "SOFR",
    "maturity": "2030-11",
    "acq": null,
    "ccy": "USD",
    "pik": false
  },
  {
    "bdc": "TSLX",
    "entity": "Elements Finco Limited",
    "company": "Elements Finco Limited",
    "desc": null,
    "sector": "Business Services",
    "type": "First Lien",
    "affil": "",
    "fv": 2255.0,
    "cost": 2270.0,
    "par": null,
    "mark": 99.34,
    "spread": 5.25,
    "rate": 8.92,
    "baseRate": "SOFR",
    "maturity": "2031-04",
    "acq": null,
    "ccy": "USD",
    "pik": true
  },
  {
    "bdc": "TSLX",
    "entity": "Elements Finco Limited",
    "company": "Elements Finco Limited",
    "desc": null,
    "sector": "Business Services",
    "type": "First Lien",
    "affil": "",
    "fv": 1821.0,
    "cost": 1842.0,
    "par": null,
    "mark": 98.86,
    "spread": 5.0,
    "rate": 8.67,
    "baseRate": "SOFR",
    "maturity": "2031-04",
    "acq": null,
    "ccy": "USD",
    "pik": false
  },
  {
    "bdc": "TSLX",
    "entity": "Elements Finco Limited",
    "company": "Elements Finco Limited",
    "desc": null,
    "sector": "Business Services",
    "type": "First Lien",
    "affil": "",
    "fv": 10514.0,
    "cost": 13193.0,
    "par": null,
    "mark": 79.69,
    "spread": 5.5,
    "rate": 9.23,
    "baseRate": "SOFR",
    "maturity": "2031-04",
    "acq": null,
    "ccy": "GBP",
    "pik": true
  },
  {
    "bdc": "TSLX",
    "entity": "ExtraHop Networks, Inc",
    "company": "ExtraHop Networks, Inc",
    "desc": null,
    "sector": "Business Services",
    "type": "First Lien",
    "affil": "",
    "fv": 75346.0,
    "cost": 75725.0,
    "par": null,
    "mark": 99.5,
    "spread": 6.6,
    "rate": 10.27,
    "baseRate": "SOFR",
    "maturity": "2027-07",
    "acq": null,
    "ccy": "USD",
    "pik": false
  },
  {
    "bdc": "TSLX",
    "entity": "ExtraHop Networks, Inc",
    "company": "ExtraHop Networks, Inc",
    "desc": null,
    "sector": "Business Services",
    "type": "First Lien",
    "affil": "",
    "fv": 880.0,
    "cost": 882.0,
    "par": null,
    "mark": 99.77,
    "spread": 6.6,
    "rate": 6.6,
    "baseRate": "SOFR",
    "maturity": "2027-07",
    "acq": null,
    "ccy": "USD",
    "pik": false
  },
  {
    "bdc": "TSLX",
    "entity": "Lynx BidCo",
    "company": "Lynx BidCo",
    "desc": null,
    "sector": "Business Services",
    "type": "First Lien",
    "affil": "",
    "fv": 1381.0,
    "cost": 1444.0,
    "par": null,
    "mark": 95.64,
    "spread": 6.25,
    "rate": 9.95,
    "baseRate": "SOFR",
    "maturity": "2031-07",
    "acq": null,
    "ccy": "USD",
    "pik": false
  },
  {
    "bdc": "TSLX",
    "entity": "Lynx BidCo",
    "company": "Lynx BidCo",
    "desc": null,
    "sector": "Business Services",
    "type": "First Lien",
    "affil": "",
    "fv": 23762.0,
    "cost": 27789.0,
    "par": null,
    "mark": 85.51,
    "spread": 6.25,
    "rate": 8.38,
    "baseRate": "EURIBOR",
    "maturity": "2031-07",
    "acq": null,
    "ccy": "EUR",
    "pik": false
  },
  {
    "bdc": "TSLX",
    "entity": "Mitnick Corporate Purchaser, Inc",
    "company": "Mitnick Corporate Purchaser, Inc",
    "desc": null,
    "sector": "Business Services",
    "type": "First Lien",
    "affil": "",
    "fv": 139.0,
    "cost": 322.0,
    "par": null,
    "mark": 43.17,
    "spread": 4.85,
    "rate": 8.52,
    "baseRate": "SOFR",
    "maturity": "2029-05",
    "acq": null,
    "ccy": "USD",
    "pik": false
  },
  {
    "bdc": "TSLX",
    "entity": "Price Fx Inc",
    "company": "Price Fx Inc",
    "desc": null,
    "sector": "Business Services",
    "type": "First Lien",
    "affil": "",
    "fv": 915.0,
    "cost": 971.0,
    "par": null,
    "mark": 94.23,
    "spread": 7.0,
    "rate": 9.04,
    "baseRate": "EURIBOR",
    "maturity": "2029-10",
    "acq": null,
    "ccy": "EUR",
    "pik": false
  },
  {
    "bdc": "TSLX",
    "entity": "Price Fx Inc",
    "company": "Price Fx Inc",
    "desc": null,
    "sector": "Business Services",
    "type": "First Lien",
    "affil": "",
    "fv": 915.0,
    "cost": 927.0,
    "par": null,
    "mark": 98.71,
    "spread": 6.25,
    "rate": 8.29,
    "baseRate": "EURIBOR",
    "maturity": "2029-10",
    "acq": null,
    "ccy": "EUR",
    "pik": false
  },
  {
    "bdc": "TSLX",
    "entity": "USA DeBusk, LLC",
    "company": "USA DeBusk, LLC",
    "desc": null,
    "sector": "Business Services",
    "type": "First Lien",
    "affil": "",
    "fv": 9519.0,
    "cost": 9356.0,
    "par": null,
    "mark": 101.74,
    "spread": 5.25,
    "rate": 8.92,
    "baseRate": "SOFR",
    "maturity": "2031-04",
    "acq": null,
    "ccy": "USD",
    "pik": false
  },
  {
    "bdc": "TSLX",
    "entity": "USA DeBusk, LLC",
    "company": "USA DeBusk, LLC",
    "desc": null,
    "sector": "Business Services",
    "type": "First Lien",
    "affil": "",
    "fv": 1030.0,
    "cost": 1010.0,
    "par": null,
    "mark": 101.98,
    "spread": 5.25,
    "rate": 8.92,
    "baseRate": "SOFR",
    "maturity": "2030-04",
    "acq": null,
    "ccy": "USD",
    "pik": false
  },
  {
    "bdc": "TSLX",
    "entity": "Wrangler TopCo, LLC",
    "company": "Wrangler TopCo, LLC",
    "desc": null,
    "sector": "Business Services",
    "type": "First Lien",
    "affil": "",
    "fv": 5954.0,
    "cost": 5866.0,
    "par": null,
    "mark": 101.5,
    "spread": 5.75,
    "rate": 9.43,
    "baseRate": "SOFR",
    "maturity": "2029-09",
    "acq": null,
    "ccy": "USD",
    "pik": false
  },
  {
    "bdc": "TSLX",
    "entity": "Erling Lux Bidco SARL",
    "company": "Erling Lux Bidco SARL",
    "desc": null,
    "sector": "Chemicals",
    "type": "First Lien",
    "affil": "",
    "fv": 11467.0,
    "cost": 11672.0,
    "par": null,
    "mark": 98.24,
    "spread": 7.0,
    "rate": 9.03,
    "baseRate": "EURIBOR",
    "maturity": "2028-09",
    "acq": null,
    "ccy": "EUR",
    "pik": false
  },
  {
    "bdc": "TSLX",
    "entity": "Erling Lux Bidco SARL",
    "company": "Erling Lux Bidco SARL",
    "desc": null,
    "sector": "Chemicals",
    "type": "First Lien",
    "affil": "",
    "fv": 19859.0,
    "cost": 23678.0,
    "par": null,
    "mark": 83.87,
    "spread": 7.0,
    "rate": 10.73,
    "baseRate": "SOFR",
    "maturity": "2028-09",
    "acq": null,
    "ccy": "GBP",
    "pik": false
  },
  {
    "bdc": "TSLX",
    "entity": "Erling Lux Bidco SARL",
    "company": "Erling Lux Bidco SARL",
    "desc": null,
    "sector": "Chemicals",
    "type": "First Lien",
    "affil": "",
    "fv": 7390.0,
    "cost": 712.0,
    "par": null,
    "mark": 1037.92,
    "spread": 7.0,
    "rate": 11.11,
    "baseRate": null,
    "maturity": "2028-09",
    "acq": null,
    "ccy": "NOK",
    "pik": false
  },
  {
    "bdc": "TSLX",
    "entity": "Erling Lux Bidco SARL",
    "company": "Erling Lux Bidco SARL",
    "desc": null,
    "sector": "Chemicals",
    "type": "First Lien",
    "affil": "",
    "fv": 632.0,
    "cost": 790.0,
    "par": null,
    "mark": 80.0,
    "spread": 7.0,
    "rate": 10.73,
    "baseRate": "SOFR",
    "maturity": "2028-09",
    "acq": null,
    "ccy": "GBP",
    "pik": false
  },
  {
    "bdc": "TSLX",
    "entity": "Aurelia Netherlands B.V",
    "company": "Aurelia Netherlands B.V",
    "desc": null,
    "sector": "Communications",
    "type": "First Lien",
    "affil": "",
    "fv": 32657.0,
    "cost": 35023.0,
    "par": null,
    "mark": 93.24,
    "spread": 4.75,
    "rate": 6.77,
    "baseRate": "EURIBOR",
    "maturity": "2031-05",
    "acq": null,
    "ccy": "EUR",
    "pik": false
  },
  {
    "bdc": "TSLX",
    "entity": "Education EMS Linq, Inc",
    "company": "Education EMS Linq, Inc",
    "desc": null,
    "sector": null,
    "type": "First Lien",
    "affil": "",
    "fv": 54249.0,
    "cost": 55825.0,
    "par": null,
    "mark": 97.18,
    "spread": 6.35,
    "rate": 10.02,
    "baseRate": "SOFR",
    "maturity": "2027-12",
    "acq": null,
    "ccy": "USD",
    "pik": false
  },
  {
    "bdc": "TSLX",
    "entity": "Education EMS Linq, Inc",
    "company": "Education EMS Linq, Inc",
    "desc": null,
    "sector": null,
    "type": "First Lien",
    "affil": "",
    "fv": 2995.0,
    "cost": 3252.0,
    "par": null,
    "mark": 92.1,
    "spread": 6.35,
    "rate": 10.02,
    "baseRate": "SOFR",
    "maturity": "2027-12",
    "acq": null,
    "ccy": "USD",
    "pik": false
  },
  {
    "bdc": "TSLX",
    "entity": "Education Kangaroo Bidco AS",
    "company": "Education Kangaroo Bidco AS",
    "desc": null,
    "sector": null,
    "type": "First Lien",
    "affil": "",
    "fv": 30275.0,
    "cost": 29979.0,
    "par": null,
    "mark": 100.99,
    "spread": 6.0,
    "rate": 9.74,
    "baseRate": "SOFR",
    "maturity": "2030-11",
    "acq": null,
    "ccy": "USD",
    "pik": false
  },
  {
    "bdc": "TSLX",
    "entity": "Education Severin Acquisition, LLC",
    "company": "Education Severin Acquisition, LLC",
    "desc": null,
    "sector": null,
    "type": "First Lien",
    "affil": "",
    "fv": 15680.0,
    "cost": 16046.0,
    "par": null,
    "mark": 97.72,
    "spread": 4.75,
    "rate": 8.42,
    "baseRate": "SOFR",
    "maturity": "2031-10",
    "acq": null,
    "ccy": "USD",
    "pik": true
  },
  {
    "bdc": "TSLX",
    "entity": "Education Severin Acquisition, LLC",
    "company": "Education Severin Acquisition, LLC",
    "desc": null,
    "sector": null,
    "type": "First Lien",
    "affil": "",
    "fv": 466.0,
    "cost": 489.0,
    "par": null,
    "mark": 95.3,
    "spread": 4.5,
    "rate": 8.18,
    "baseRate": "SOFR",
    "maturity": "2031-10",
    "acq": null,
    "ccy": "USD",
    "pik": false
  },
  {
    "bdc": "TSLX",
    "entity": "Electronics Sapphire Software Buyer, Inc",
    "company": "Electronics Sapphire Software Buyer, Inc",
    "desc": null,
    "sector": null,
    "type": "First Lien",
    "affil": "",
    "fv": 26068.0,
    "cost": 26653.0,
    "par": null,
    "mark": 97.81,
    "spread": 5.0,
    "rate": 8.7,
    "baseRate": "SOFR",
    "maturity": "2031-09",
    "acq": null,
    "ccy": "USD",
    "pik": false
  },
  {
    "bdc": "TSLX",
    "entity": "Alaska Bidco Oy",
    "company": "Alaska Bidco Oy",
    "desc": null,
    "sector": "Financial Services",
    "type": "First Lien",
    "affil": "",
    "fv": 732.0,
    "cost": 764.0,
    "par": null,
    "mark": 95.81,
    "spread": 5.75,
    "rate": 7.84,
    "baseRate": "EURIBOR",
    "maturity": "2030-05",
    "acq": null,
    "ccy": "EUR",
    "pik": false
  },
  {
    "bdc": "TSLX",
    "entity": "Arlberg Bidco LLC",
    "company": "Arlberg Bidco LLC",
    "desc": null,
    "sector": "Financial Services",
    "type": "First Lien",
    "affil": "",
    "fv": 4913.0,
    "cost": 4906.0,
    "par": null,
    "mark": 100.14,
    "spread": 5.75,
    "rate": 9.4,
    "baseRate": "SOFR",
    "maturity": "2031-02",
    "acq": null,
    "ccy": "USD",
    "pik": false
  },
  {
    "bdc": "TSLX",
    "entity": "GreenShoot BidCo B.V",
    "company": "GreenShoot BidCo B.V",
    "desc": null,
    "sector": "Financial Services",
    "type": "First Lien",
    "affil": "",
    "fv": 4979.0,
    "cost": 5442.0,
    "par": null,
    "mark": 91.49,
    "spread": 5.75,
    "rate": 7.76,
    "baseRate": "EURIBOR",
    "maturity": "2030-05",
    "acq": null,
    "ccy": "EUR",
    "pik": false
  },
  {
    "bdc": "TSLX",
    "entity": "GreenShoot BidCo B.V",
    "company": "GreenShoot BidCo B.V",
    "desc": null,
    "sector": "Financial Services",
    "type": "First Lien",
    "affil": "",
    "fv": 69.0,
    "cost": 79.0,
    "par": null,
    "mark": 87.34,
    "spread": 5.75,
    "rate": 7.76,
    "baseRate": "EURIBOR",
    "maturity": "2030-05",
    "acq": null,
    "ccy": "EUR",
    "pik": false
  },
  {
    "bdc": "TSLX",
    "entity": "Ibis Intermediate Co",
    "company": "Ibis Intermediate Co",
    "desc": null,
    "sector": "Financial Services",
    "type": "First Lien",
    "affil": "",
    "fv": 1169.0,
    "cost": 1150.0,
    "par": null,
    "mark": 101.65,
    "spread": 4.65,
    "rate": 8.32,
    "baseRate": "SOFR",
    "maturity": "2027-05",
    "acq": null,
    "ccy": "USD",
    "pik": false
  },
  {
    "bdc": "TSLX",
    "entity": "Ibis US Blocker Co",
    "company": "Ibis US Blocker Co",
    "desc": null,
    "sector": "Financial Services",
    "type": "First Lien",
    "affil": "",
    "fv": 21534.0,
    "cost": 21575.0,
    "par": null,
    "mark": 99.81,
    "spread": 8.5,
    "rate": 12.13,
    "baseRate": "SOFR",
    "maturity": "2028-05",
    "acq": null,
    "ccy": "USD",
    "pik": true
  },
  {
    "bdc": "TSLX",
    "entity": "Passport Labs, Inc",
    "company": "Passport Labs, Inc",
    "desc": null,
    "sector": "Financial Services",
    "type": "",
    "affil": "",
    "fv": 2348.0,
    "cost": 1086.0,
    "par": null,
    "mark": 216.21,
    "spread": null,
    "rate": 8.0,
    "baseRate": null,
    "maturity": "2026-08",
    "acq": null,
    "ccy": "USD",
    "pik": false
  },
  {
    "bdc": "TSLX",
    "entity": "Payroc Buyer, LLC",
    "company": "Payroc Buyer, LLC",
    "desc": null,
    "sector": "Financial Services",
    "type": "",
    "affil": "",
    "fv": 5188.0,
    "cost": 6086.0,
    "par": null,
    "mark": 85.24,
    "spread": null,
    "rate": 5.5,
    "baseRate": null,
    "maturity": "2030-09",
    "acq": null,
    "ccy": "USD",
    "pik": true
  },
  {
    "bdc": "TSLX",
    "entity": "TS Imagine, Inc",
    "company": "TS Imagine, Inc",
    "desc": null,
    "sector": "Financial Services",
    "type": "First Lien",
    "affil": "",
    "fv": 54133.0,
    "cost": 54466.0,
    "par": null,
    "mark": 99.39,
    "spread": 5.85,
    "rate": 9.52,
    "baseRate": "SOFR",
    "maturity": "2027-04",
    "acq": null,
    "ccy": "USD",
    "pik": false
  },
  {
    "bdc": "TSLX",
    "entity": "TS Imagine, Inc",
    "company": "TS Imagine, Inc",
    "desc": null,
    "sector": "Financial Services",
    "type": "First Lien",
    "affil": "",
    "fv": 1211.0,
    "cost": 1221.0,
    "par": null,
    "mark": 99.18,
    "spread": 4.75,
    "rate": 11.5,
    "baseRate": "Prime",
    "maturity": "2027-05",
    "acq": null,
    "ccy": "USD",
    "pik": false
  },
  {
    "bdc": "TSLX",
    "entity": "Volante Technologies, Inc",
    "company": "Volante Technologies, Inc",
    "desc": null,
    "sector": "Financial Services",
    "type": "First Lien",
    "affil": "",
    "fv": 3957.0,
    "cost": 3752.0,
    "par": null,
    "mark": 105.46,
    "spread": null,
    "rate": 16.5,
    "baseRate": null,
    "maturity": "2028-09",
    "acq": null,
    "ccy": "USD",
    "pik": true
  },
  {
    "bdc": "TSLX",
    "entity": "Aledade Inc",
    "company": "Aledade Inc",
    "desc": null,
    "sector": "Healthcare",
    "type": "First Lien",
    "affil": "",
    "fv": 11725.0,
    "cost": 11942.0,
    "par": null,
    "mark": 98.18,
    "spread": 5.75,
    "rate": 9.42,
    "baseRate": "SOFR",
    "maturity": "2028-11",
    "acq": null,
    "ccy": "USD",
    "pik": false
  },
  {
    "bdc": "TSLX",
    "entity": "BCTO Ace Purchaser, Inc",
    "company": "BCTO Ace Purchaser, Inc",
    "desc": null,
    "sector": "Healthcare",
    "type": "First Lien",
    "affil": "",
    "fv": 72608.0,
    "cost": 71468.0,
    "par": null,
    "mark": 101.6,
    "spread": 6.5,
    "rate": 10.17,
    "baseRate": "SOFR",
    "maturity": "2029-11",
    "acq": null,
    "ccy": "USD",
    "pik": false
  },
  {
    "bdc": "TSLX",
    "entity": "BCTO Ace Purchaser, Inc",
    "company": "BCTO Ace Purchaser, Inc",
    "desc": null,
    "sector": "Healthcare",
    "type": "Second Lien",
    "affil": "",
    "fv": 8354.0,
    "cost": 7874.0,
    "par": null,
    "mark": 106.1,
    "spread": 10.7,
    "rate": 14.37,
    "baseRate": "SOFR",
    "maturity": "2030-01",
    "acq": null,
    "ccy": "USD",
    "pik": true
  },
  {
    "bdc": "TSLX",
    "entity": "Eventus Buyer, LLC",
    "company": "Eventus Buyer, LLC",
    "desc": null,
    "sector": "Healthcare",
    "type": "First Lien",
    "affil": "",
    "fv": 28577.0,
    "cost": 28340.0,
    "par": null,
    "mark": 100.84,
    "spread": 5.5,
    "rate": 9.17,
    "baseRate": "SOFR",
    "maturity": "2030-11",
    "acq": null,
    "ccy": "USD",
    "pik": false
  },
  {
    "bdc": "TSLX",
    "entity": "Eventus Buyer, LLC",
    "company": "Eventus Buyer, LLC",
    "desc": null,
    "sector": "Healthcare",
    "type": "First Lien",
    "affil": "",
    "fv": 922.0,
    "cost": 893.0,
    "par": null,
    "mark": 103.25,
    "spread": 5.5,
    "rate": 9.17,
    "baseRate": "SOFR",
    "maturity": "2030-11",
    "acq": null,
    "ccy": "USD",
    "pik": false
  },
  {
    "bdc": "TSLX",
    "entity": "HMP Omnimedia, LLC",
    "company": "HMP Omnimedia, LLC",
    "desc": null,
    "sector": "Healthcare",
    "type": "First Lien",
    "affil": "",
    "fv": 19450.0,
    "cost": 19264.0,
    "par": null,
    "mark": 100.97,
    "spread": 5.25,
    "rate": 8.92,
    "baseRate": "SOFR",
    "maturity": "2032-07",
    "acq": null,
    "ccy": "USD",
    "pik": false
  },
  {
    "bdc": "TSLX",
    "entity": "Ingenovis Health Finance, LLC",
    "company": "Ingenovis Health Finance, LLC",
    "desc": null,
    "sector": "Healthcare",
    "type": "First Lien",
    "affil": "",
    "fv": 31850.0,
    "cost": 31430.0,
    "par": null,
    "mark": 101.34,
    "spread": 6.0,
    "rate": 9.67,
    "baseRate": "SOFR",
    "maturity": "2030-05",
    "acq": null,
    "ccy": "USD",
    "pik": false
  },
  {
    "bdc": "TSLX",
    "entity": "LIHA Holdco B.V",
    "company": "LIHA Holdco B.V",
    "desc": null,
    "sector": "Healthcare",
    "type": "First Lien",
    "affil": "",
    "fv": 5829.0,
    "cost": 6214.0,
    "par": null,
    "mark": 93.8,
    "spread": 6.5,
    "rate": 8.63,
    "baseRate": "EURIBOR",
    "maturity": "2029-02",
    "acq": null,
    "ccy": "EUR",
    "pik": false
  },
  {
    "bdc": "TSLX",
    "entity": "LIHA Holdco B.V",
    "company": "LIHA Holdco B.V",
    "desc": null,
    "sector": "Healthcare",
    "type": "First Lien",
    "affil": "",
    "fv": 313.0,
    "cost": 363.0,
    "par": null,
    "mark": 86.23,
    "spread": 6.5,
    "rate": 8.63,
    "baseRate": "EURIBOR",
    "maturity": "2029-02",
    "acq": null,
    "ccy": "EUR",
    "pik": false
  },
  {
    "bdc": "TSLX",
    "entity": "Raptor US Buyer II Corp",
    "company": "Raptor US Buyer II Corp",
    "desc": null,
    "sector": "Healthcare",
    "type": "First Lien",
    "affil": "",
    "fv": 17858.0,
    "cost": 17602.0,
    "par": null,
    "mark": 101.45,
    "spread": 6.25,
    "rate": 9.92,
    "baseRate": "SOFR",
    "maturity": "2029-03",
    "acq": null,
    "ccy": "USD",
    "pik": false
  },
  {
    "bdc": "TSLX",
    "entity": "Raptor US Buyer II Corp",
    "company": "Raptor US Buyer II Corp",
    "desc": null,
    "sector": "Healthcare",
    "type": "First Lien",
    "affil": "",
    "fv": 80.0,
    "cost": 76.0,
    "par": null,
    "mark": 105.26,
    "spread": 6.25,
    "rate": 9.92,
    "baseRate": "SOFR",
    "maturity": "2029-03",
    "acq": null,
    "ccy": "USD",
    "pik": false
  },
  {
    "bdc": "TSLX",
    "entity": "Symplr Software Inc",
    "company": "Symplr Software Inc",
    "desc": null,
    "sector": "Healthcare",
    "type": "First Lien",
    "affil": "",
    "fv": 443.0,
    "cost": 559.0,
    "par": null,
    "mark": 79.25,
    "spread": 4.6,
    "rate": 8.27,
    "baseRate": "SOFR",
    "maturity": "2027-12",
    "acq": null,
    "ccy": "USD",
    "pik": false
  },
  {
    "bdc": "TSLX",
    "entity": "Velocity Clinical Research, Inc",
    "company": "Velocity Clinical Research, Inc",
    "desc": null,
    "sector": "Healthcare",
    "type": "First Lien",
    "affil": "",
    "fv": 62808.0,
    "cost": 62763.0,
    "par": null,
    "mark": 100.07,
    "spread": 7.5,
    "rate": 11.2,
    "baseRate": "SOFR",
    "maturity": "2031-09",
    "acq": null,
    "ccy": "USD",
    "pik": false
  },
  {
    "bdc": "TSLX",
    "entity": "Velocity Clinical Research, Inc",
    "company": "Velocity Clinical Research, Inc",
    "desc": null,
    "sector": "Healthcare",
    "type": "First Lien",
    "affil": "",
    "fv": 481.0,
    "cost": 471.0,
    "par": null,
    "mark": 102.12,
    "spread": 7.5,
    "rate": 11.2,
    "baseRate": "SOFR",
    "maturity": "2031-09",
    "acq": null,
    "ccy": "USD",
    "pik": false
  },
  {
    "bdc": "TSLX",
    "entity": "ASG II, LLC",
    "company": "ASG II, LLC",
    "desc": null,
    "sector": "Hotel, Gaming and Leisure",
    "type": "First Lien",
    "affil": "",
    "fv": 62887.0,
    "cost": 64324.0,
    "par": null,
    "mark": 97.77,
    "spread": 6.4,
    "rate": 10.07,
    "baseRate": "SOFR",
    "maturity": "2028-05",
    "acq": null,
    "ccy": "USD",
    "pik": false
  },
  {
    "bdc": "TSLX",
    "entity": "AVSC Holding Corp",
    "company": "AVSC Holding Corp",
    "desc": null,
    "sector": "Hotel, Gaming and Leisure",
    "type": "First Lien",
    "affil": "",
    "fv": 44492.0,
    "cost": 43951.0,
    "par": null,
    "mark": 101.23,
    "spread": 5.0,
    "rate": 8.67,
    "baseRate": "SOFR",
    "maturity": "2031-12",
    "acq": null,
    "ccy": "USD",
    "pik": false
  },
  {
    "bdc": "TSLX",
    "entity": "AVSC Holding Corp",
    "company": "AVSC Holding Corp",
    "desc": null,
    "sector": "Hotel, Gaming and Leisure",
    "type": "First Lien",
    "affil": "",
    "fv": 846.0,
    "cost": 799.0,
    "par": null,
    "mark": 105.88,
    "spread": 5.0,
    "rate": 8.67,
    "baseRate": "SOFR",
    "maturity": "2029-12",
    "acq": null,
    "ccy": "USD",
    "pik": false
  },
  {
    "bdc": "TSLX",
    "entity": "Equinox Holdings, Inc",
    "company": "Equinox Holdings, Inc",
    "desc": null,
    "sector": "Hotel, Gaming and Leisure",
    "type": "First Lien",
    "affil": "",
    "fv": 53396.0,
    "cost": 51544.0,
    "par": null,
    "mark": 103.59,
    "spread": 7.25,
    "rate": 10.95,
    "baseRate": "SOFR",
    "maturity": "2029-03",
    "acq": null,
    "ccy": "USD",
    "pik": false
  },
  {
    "bdc": "TSLX",
    "entity": "Equinox Holdings, Inc",
    "company": "Equinox Holdings, Inc",
    "desc": null,
    "sector": "Hotel, Gaming and Leisure",
    "type": "Second Lien",
    "affil": "",
    "fv": 3204.0,
    "cost": 2827.0,
    "par": null,
    "mark": 113.34,
    "spread": null,
    "rate": 16.0,
    "baseRate": null,
    "maturity": "2027-06",
    "acq": null,
    "ccy": "USD",
    "pik": true
  },
  {
    "bdc": "TSLX",
    "entity": "IRGSE Holding Corp",
    "company": "IRGSE Holding Corp",
    "desc": null,
    "sector": "Hotel, Gaming and Leisure",
    "type": "First Lien",
    "affil": "",
    "fv": 29202.0,
    "cost": 28594.0,
    "par": null,
    "mark": 102.13,
    "spread": 9.65,
    "rate": 13.35,
    "baseRate": "SOFR",
    "maturity": "2026-06",
    "acq": null,
    "ccy": "USD",
    "pik": false
  },
  {
    "bdc": "TSLX",
    "entity": "IRGSE Holding Corp",
    "company": "IRGSE Holding Corp",
    "desc": null,
    "sector": "Hotel, Gaming and Leisure",
    "type": "First Lien",
    "affil": "",
    "fv": 29135.0,
    "cost": 30313.0,
    "par": null,
    "mark": 96.11,
    "spread": 9.65,
    "rate": 13.33,
    "baseRate": "SOFR",
    "maturity": "2026-06",
    "acq": null,
    "ccy": "USD",
    "pik": false
  },
  {
    "bdc": "TSLX",
    "entity": "Mindbody, Inc",
    "company": "Mindbody, Inc",
    "desc": null,
    "sector": "Hotel, Gaming and Leisure",
    "type": "First Lien",
    "affil": "",
    "fv": 28401.0,
    "cost": 28401.0,
    "par": null,
    "mark": 100.0,
    "spread": 6.0,
    "rate": 9.7,
    "baseRate": "SOFR",
    "maturity": "2033-03",
    "acq": null,
    "ccy": "USD",
    "pik": false
  },
  {
    "bdc": "TSLX",
    "entity": "Sport Alliance GmbH",
    "company": "Sport Alliance GmbH",
    "desc": null,
    "sector": "Hotel, Gaming and Leisure",
    "type": "First Lien",
    "affil": "",
    "fv": 36939.0,
    "cost": 42509.0,
    "par": null,
    "mark": 86.9,
    "spread": 7.75,
    "rate": 9.77,
    "baseRate": "EURIBOR",
    "maturity": "2030-04",
    "acq": null,
    "ccy": "EUR",
    "pik": true
  },
  {
    "bdc": "TSLX",
    "entity": "Sport Alliance GmbH",
    "company": "Sport Alliance GmbH",
    "desc": null,
    "sector": "Hotel, Gaming and Leisure",
    "type": "First Lien",
    "affil": "",
    "fv": 207.0,
    "cost": 213.0,
    "par": null,
    "mark": 97.18,
    "spread": 7.25,
    "rate": 9.38,
    "baseRate": "EURIBOR",
    "maturity": "2030-04",
    "acq": null,
    "ccy": "EUR",
    "pik": false
  },
  {
    "bdc": "TSLX",
    "entity": "Axonify, Inc",
    "company": "Axonify, Inc",
    "desc": null,
    "sector": "Human Resource Support Services",
    "type": "First Lien",
    "affil": "",
    "fv": 44550.0,
    "cost": 44897.0,
    "par": null,
    "mark": 99.23,
    "spread": 6.65,
    "rate": 10.31,
    "baseRate": "SOFR",
    "maturity": "2027-05",
    "acq": null,
    "ccy": "USD",
    "pik": false
  },
  {
    "bdc": "TSLX",
    "entity": "bswift, LLC",
    "company": "bswift, LLC",
    "desc": null,
    "sector": "Human Resource Support Services",
    "type": "First Lien",
    "affil": "",
    "fv": 54081.0,
    "cost": 53847.0,
    "par": null,
    "mark": 100.43,
    "spread": 4.75,
    "rate": 8.41,
    "baseRate": "SOFR",
    "maturity": "2028-11",
    "acq": null,
    "ccy": "USD",
    "pik": false
  },
  {
    "bdc": "TSLX",
    "entity": "Elysian Finco Ltd",
    "company": "Elysian Finco Ltd",
    "desc": null,
    "sector": "Human Resource Support Services",
    "type": "First Lien",
    "affil": "",
    "fv": 21072.0,
    "cost": 21494.0,
    "par": null,
    "mark": 98.04,
    "spread": 5.15,
    "rate": 8.85,
    "baseRate": "SOFR",
    "maturity": "2028-01",
    "acq": null,
    "ccy": "USD",
    "pik": false
  },
  {
    "bdc": "TSLX",
    "entity": "Elysian Finco Ltd",
    "company": "Elysian Finco Ltd",
    "desc": null,
    "sector": "Human Resource Support Services",
    "type": "First Lien",
    "affil": "",
    "fv": 743.0,
    "cost": 1028.0,
    "par": null,
    "mark": 72.28,
    "spread": 4.0,
    "rate": 7.73,
    "baseRate": "SOFR",
    "maturity": "2028-01",
    "acq": null,
    "ccy": "GBP",
    "pik": false
  },
  {
    "bdc": "TSLX",
    "entity": "HireVue, Inc",
    "company": "HireVue, Inc",
    "desc": null,
    "sector": "Human Resource Support Services",
    "type": "First Lien",
    "affil": "",
    "fv": 50090.0,
    "cost": 54119.0,
    "par": null,
    "mark": 92.56,
    "spread": 7.75,
    "rate": 11.42,
    "baseRate": "SOFR",
    "maturity": "2029-05",
    "acq": null,
    "ccy": "USD",
    "pik": false
  },
  {
    "bdc": "TSLX",
    "entity": "HireVue, Inc",
    "company": "HireVue, Inc",
    "desc": null,
    "sector": "Human Resource Support Services",
    "type": "First Lien",
    "affil": "",
    "fv": 6331.0,
    "cost": 6854.0,
    "par": null,
    "mark": 92.37,
    "spread": 7.75,
    "rate": 11.42,
    "baseRate": "SOFR",
    "maturity": "2029-05",
    "acq": null,
    "ccy": "USD",
    "pik": false
  },
  {
    "bdc": "TSLX",
    "entity": "PayScale Holdings, Inc",
    "company": "PayScale Holdings, Inc",
    "desc": null,
    "sector": "Human Resource Support Services",
    "type": "First Lien",
    "affil": "",
    "fv": 73584.0,
    "cost": 74564.0,
    "par": null,
    "mark": 98.69,
    "spread": 5.25,
    "rate": 8.95,
    "baseRate": "SOFR",
    "maturity": "2029-10",
    "acq": null,
    "ccy": "USD",
    "pik": false
  },
  {
    "bdc": "TSLX",
    "entity": "Arrow Buyer, Inc",
    "company": "Arrow Buyer, Inc",
    "desc": null,
    "sector": "Internet Services",
    "type": "First Lien",
    "affil": "",
    "fv": 36192.0,
    "cost": 35928.0,
    "par": null,
    "mark": 100.73,
    "spread": 5.0,
    "rate": 8.7,
    "baseRate": "SOFR",
    "maturity": "2030-07",
    "acq": null,
    "ccy": "USD",
    "pik": false
  },
  {
    "bdc": "TSLX",
    "entity": "Bayshore Intermediate #2, L.P",
    "company": "Bayshore Intermediate #2, L.P",
    "desc": null,
    "sector": "Internet Services",
    "type": "First Lien",
    "affil": "",
    "fv": 41639.0,
    "cost": 42201.0,
    "par": null,
    "mark": 98.67,
    "spread": 5.5,
    "rate": 9.18,
    "baseRate": "SOFR",
    "maturity": "2028-10",
    "acq": null,
    "ccy": "USD",
    "pik": true
  },
  {
    "bdc": "TSLX",
    "entity": "Bayshore Intermediate #2, L.P",
    "company": "Bayshore Intermediate #2, L.P",
    "desc": null,
    "sector": "Internet Services",
    "type": "First Lien",
    "affil": "",
    "fv": 829.0,
    "cost": 888.0,
    "par": null,
    "mark": 93.36,
    "spread": 5.0,
    "rate": 8.69,
    "baseRate": "SOFR",
    "maturity": "2027-10",
    "acq": null,
    "ccy": "USD",
    "pik": false
  },
  {
    "bdc": "TSLX",
    "entity": "Big Wombat Holdings, Inc",
    "company": "Big Wombat Holdings, Inc",
    "desc": null,
    "sector": "Internet Services",
    "type": "First Lien",
    "affil": "",
    "fv": 46129.0,
    "cost": 46583.0,
    "par": null,
    "mark": 99.03,
    "spread": 7.0,
    "rate": 10.67,
    "baseRate": "SOFR",
    "maturity": "2031-04",
    "acq": null,
    "ccy": "USD",
    "pik": false
  },
  {
    "bdc": "TSLX",
    "entity": "Coupa Holdings, LLC",
    "company": "Coupa Holdings, LLC",
    "desc": null,
    "sector": "Internet Services",
    "type": "First Lien",
    "affil": "",
    "fv": 41450.0,
    "cost": 41780.0,
    "par": null,
    "mark": 99.21,
    "spread": 5.25,
    "rate": 8.92,
    "baseRate": "SOFR",
    "maturity": "2030-02",
    "acq": null,
    "ccy": "USD",
    "pik": false
  },
  {
    "bdc": "TSLX",
    "entity": "EDB Parent, LLC",
    "company": "EDB Parent, LLC",
    "desc": null,
    "sector": "Internet Services",
    "type": "First Lien",
    "affil": "",
    "fv": 77333.0,
    "cost": 77911.0,
    "par": null,
    "mark": 99.26,
    "spread": 7.0,
    "rate": 10.67,
    "baseRate": "SOFR",
    "maturity": "2028-07",
    "acq": null,
    "ccy": "USD",
    "pik": false
  },
  {
    "bdc": "TSLX",
    "entity": "Flight Intermediate HoldCo, Inc",
    "company": "Flight Intermediate HoldCo, Inc",
    "desc": null,
    "sector": "Internet Services",
    "type": "First Lien",
    "affil": "",
    "fv": 40000.0,
    "cost": 39192.0,
    "par": null,
    "mark": 102.06,
    "spread": null,
    "rate": 11.5,
    "baseRate": null,
    "maturity": "2030-04",
    "acq": null,
    "ccy": "USD",
    "pik": false
  },
  {
    "bdc": "TSLX",
    "entity": "Hippo XPA Bidco AB",
    "company": "Hippo XPA Bidco AB",
    "desc": null,
    "sector": "Internet Services",
    "type": "First Lien",
    "affil": "",
    "fv": 213894.0,
    "cost": 21543.0,
    "par": null,
    "mark": 992.87,
    "spread": 6.75,
    "rate": 8.94,
    "baseRate": "STIBOR",
    "maturity": "2031-02",
    "acq": null,
    "ccy": "SEK",
    "pik": true
  },
  {
    "bdc": "TSLX",
    "entity": "Hippo XPA Bidco AB",
    "company": "Hippo XPA Bidco AB",
    "desc": null,
    "sector": "Internet Services",
    "type": "First Lien",
    "affil": "",
    "fv": 2575.0,
    "cost": 2786.0,
    "par": null,
    "mark": 92.43,
    "spread": 6.75,
    "rate": 8.88,
    "baseRate": "EURIBOR",
    "maturity": "2031-02",
    "acq": null,
    "ccy": "EUR",
    "pik": true
  },
  {
    "bdc": "TSLX",
    "entity": "Hippo XPA Bidco AB",
    "company": "Hippo XPA Bidco AB",
    "desc": null,
    "sector": "Internet Services",
    "type": "First Lien",
    "affil": "",
    "fv": 3789.0,
    "cost": 385.0,
    "par": null,
    "mark": 984.16,
    "spread": 6.25,
    "rate": 8.44,
    "baseRate": "STIBOR",
    "maturity": "2031-02",
    "acq": null,
    "ccy": "SEK",
    "pik": false
  },
  {
    "bdc": "TSLX",
    "entity": "Kaseware Intermediate Holding Company",
    "company": "Kaseware Intermediate Holding Company",
    "desc": null,
    "sector": "Internet Services",
    "type": "First Lien",
    "affil": "",
    "fv": 43590.0,
    "cost": 44195.0,
    "par": null,
    "mark": 98.63,
    "spread": 5.5,
    "rate": 9.17,
    "baseRate": "SOFR",
    "maturity": "2031-10",
    "acq": null,
    "ccy": "USD",
    "pik": false
  },
  {
    "bdc": "TSLX",
    "entity": "Khoros, LLC",
    "company": "Khoros, LLC",
    "desc": null,
    "sector": "Internet Services",
    "type": "First Lien",
    "affil": "",
    "fv": 11595.0,
    "cost": 11682.0,
    "par": null,
    "mark": 99.26,
    "spread": null,
    "rate": 10.0,
    "baseRate": null,
    "maturity": "2030-05",
    "acq": null,
    "ccy": "USD",
    "pik": false
  },
  {
    "bdc": "TSLX",
    "entity": "Kryptona BidCo US, LLC",
    "company": "Kryptona BidCo US, LLC",
    "desc": null,
    "sector": "Internet Services",
    "type": "First Lien",
    "affil": "",
    "fv": 20532.0,
    "cost": 20392.0,
    "par": null,
    "mark": 100.69,
    "spread": 6.0,
    "rate": 9.44,
    "baseRate": "SOFR",
    "maturity": "2031-12",
    "acq": null,
    "ccy": "USD",
    "pik": true
  },
  {
    "bdc": "TSLX",
    "entity": "Kryptona BidCo US, LLC",
    "company": "Kryptona BidCo US, LLC",
    "desc": null,
    "sector": "Internet Services",
    "type": "First Lien",
    "affil": "",
    "fv": 4757.0,
    "cost": 4972.0,
    "par": null,
    "mark": 95.68,
    "spread": 5.75,
    "rate": 8.06,
    "baseRate": "EURIBOR",
    "maturity": "2031-12",
    "acq": null,
    "ccy": "EUR",
    "pik": true
  },
  {
    "bdc": "TSLX",
    "entity": "LeanTaaS Holdings, Inc",
    "company": "LeanTaaS Holdings, Inc",
    "desc": null,
    "sector": "Internet Services",
    "type": "First Lien",
    "affil": "",
    "fv": 62210.0,
    "cost": 62946.0,
    "par": null,
    "mark": 98.83,
    "spread": 7.75,
    "rate": 11.45,
    "baseRate": "SOFR",
    "maturity": "2028-07",
    "acq": null,
    "ccy": "USD",
    "pik": false
  },
  {
    "bdc": "TSLX",
    "entity": "RainFocus, LLC",
    "company": "RainFocus, LLC",
    "desc": null,
    "sector": "Internet Services",
    "type": "First Lien",
    "affil": "",
    "fv": 65144.0,
    "cost": 65309.0,
    "par": null,
    "mark": 99.75,
    "spread": 6.38,
    "rate": 10.12,
    "baseRate": "SOFR",
    "maturity": "2031-04",
    "acq": null,
    "ccy": "USD",
    "pik": false
  },
  {
    "bdc": "TSLX",
    "entity": "SMA Technologies Holdings, LLC",
    "company": "SMA Technologies Holdings, LLC",
    "desc": null,
    "sector": "Internet Services",
    "type": "First Lien",
    "affil": "",
    "fv": 55579.0,
    "cost": 54523.0,
    "par": null,
    "mark": 101.94,
    "spread": 6.5,
    "rate": 10.17,
    "baseRate": "SOFR",
    "maturity": "2028-10",
    "acq": null,
    "ccy": "USD",
    "pik": false
  },
  {
    "bdc": "TSLX",
    "entity": "Arcwood Environmental, Inc",
    "company": "Arcwood Environmental, Inc",
    "desc": null,
    "sector": "Manufacturing",
    "type": "First Lien",
    "affil": "",
    "fv": 12130.0,
    "cost": 12081.0,
    "par": null,
    "mark": 100.41,
    "spread": 5.25,
    "rate": 8.92,
    "baseRate": "SOFR",
    "maturity": "2031-01",
    "acq": null,
    "ccy": "USD",
    "pik": false
  },
  {
    "bdc": "TSLX",
    "entity": "Arcwood Environmental, Inc",
    "company": "Arcwood Environmental, Inc",
    "desc": null,
    "sector": "Manufacturing",
    "type": "First Lien",
    "affil": "",
    "fv": 3759.0,
    "cost": 3742.0,
    "par": null,
    "mark": 100.45,
    "spread": 5.0,
    "rate": 8.69,
    "baseRate": "SOFR",
    "maturity": "2031-01",
    "acq": null,
    "ccy": "USD",
    "pik": false
  },
  {
    "bdc": "TSLX",
    "entity": "ASP Unifrax Holdings, Inc",
    "company": "ASP Unifrax Holdings, Inc",
    "desc": null,
    "sector": "Manufacturing",
    "type": "First Lien",
    "affil": "",
    "fv": 2002.0,
    "cost": 3604.0,
    "par": null,
    "mark": 55.55,
    "spread": 7.75,
    "rate": 11.45,
    "baseRate": "SOFR",
    "maturity": "2029-09",
    "acq": null,
    "ccy": "USD",
    "pik": true
  },
  {
    "bdc": "TSLX",
    "entity": "ASP Unifrax Holdings, Inc",
    "company": "ASP Unifrax Holdings, Inc",
    "desc": null,
    "sector": "Manufacturing",
    "type": "Second Lien",
    "affil": "",
    "fv": 122.0,
    "cost": 1529.0,
    "par": null,
    "mark": 7.98,
    "spread": null,
    "rate": 7.1,
    "baseRate": null,
    "maturity": "2029-09",
    "acq": null,
    "ccy": "USD",
    "pik": true
  },
  {
    "bdc": "TSLX",
    "entity": "Leg Purchaser, Inc",
    "company": "Leg Purchaser, Inc",
    "desc": null,
    "sector": "Manufacturing",
    "type": "First Lien",
    "affil": "",
    "fv": 56262.0,
    "cost": 56604.0,
    "par": null,
    "mark": 99.4,
    "spread": 5.5,
    "rate": 9.15,
    "baseRate": "SOFR",
    "maturity": "2032-01",
    "acq": null,
    "ccy": "USD",
    "pik": false
  },
  {
    "bdc": "TSLX",
    "entity": "Varinem German BidCo GMBH",
    "company": "Varinem German BidCo GMBH",
    "desc": null,
    "sector": "Manufacturing",
    "type": "First Lien",
    "affil": "",
    "fv": 12791.0,
    "cost": 13704.0,
    "par": null,
    "mark": 93.34,
    "spread": 5.5,
    "rate": 7.63,
    "baseRate": "EURIBOR",
    "maturity": "2031-07",
    "acq": null,
    "ccy": "EUR",
    "pik": false
  },
  {
    "bdc": "TSLX",
    "entity": "Varinem German BidCo GMBH",
    "company": "Varinem German BidCo GMBH",
    "desc": null,
    "sector": "Manufacturing",
    "type": "First Lien",
    "affil": "",
    "fv": 5173.0,
    "cost": 5644.0,
    "par": null,
    "mark": 91.65,
    "spread": 4.75,
    "rate": 6.88,
    "baseRate": "EURIBOR",
    "maturity": "2031-07",
    "acq": null,
    "ccy": "EUR",
    "pik": false
  },
  {
    "bdc": "TSLX",
    "entity": "Office Products USR Parent, Inc",
    "company": "Office Products USR Parent, Inc",
    "desc": null,
    "sector": null,
    "type": "First Lien",
    "affil": "",
    "fv": 9263.0,
    "cost": 9242.0,
    "par": null,
    "mark": 100.23,
    "spread": 6.5,
    "rate": 10.17,
    "baseRate": "SOFR",
    "maturity": "2027-04",
    "acq": null,
    "ccy": "USD",
    "pik": false
  },
  {
    "bdc": "TSLX",
    "entity": "Laramie Energy, LLC",
    "company": "Laramie Energy, LLC",
    "desc": null,
    "sector": "Oil, Gas and Consumable Fuels",
    "type": "First Lien",
    "affil": "",
    "fv": 27522.0,
    "cost": 27196.0,
    "par": null,
    "mark": 101.2,
    "spread": 7.1,
    "rate": 10.77,
    "baseRate": "SOFR",
    "maturity": "2027-02",
    "acq": null,
    "ccy": "USD",
    "pik": false
  },
  {
    "bdc": "TSLX",
    "entity": "TRP Assets, LLC",
    "company": "TRP Assets, LLC",
    "desc": null,
    "sector": "Oil, Gas and Consumable Fuels",
    "type": "First Lien",
    "affil": "",
    "fv": 55809.0,
    "cost": 53936.0,
    "par": null,
    "mark": 103.47,
    "spread": 7.0,
    "rate": 10.7,
    "baseRate": "SOFR",
    "maturity": "2029-12",
    "acq": null,
    "ccy": "USD",
    "pik": false
  },
  {
    "bdc": "TSLX",
    "entity": "Other Bor\u00e9al Bidco",
    "company": "Other Bor\u00e9al Bidco",
    "desc": null,
    "sector": null,
    "type": "First Lien",
    "affil": "",
    "fv": 13535.0,
    "cost": 14626.0,
    "par": null,
    "mark": 92.54,
    "spread": 7.0,
    "rate": 9.13,
    "baseRate": "EURIBOR",
    "maturity": "2032-03",
    "acq": null,
    "ccy": "EUR",
    "pik": true
  },
  {
    "bdc": "TSLX",
    "entity": "Other Kahua, Inc",
    "company": "Other Kahua, Inc",
    "desc": null,
    "sector": null,
    "type": "First Lien",
    "affil": "",
    "fv": 30000.0,
    "cost": 29685.0,
    "par": null,
    "mark": 101.06,
    "spread": 6.0,
    "rate": 9.67,
    "baseRate": "SOFR",
    "maturity": "2030-08",
    "acq": null,
    "ccy": "USD",
    "pik": false
  },
  {
    "bdc": "TSLX",
    "entity": "Other Omnigo Software, LLC",
    "company": "Other Omnigo Software, LLC",
    "desc": null,
    "sector": null,
    "type": "First Lien",
    "affil": "",
    "fv": 12793.0,
    "cost": 13023.0,
    "par": null,
    "mark": 98.23,
    "spread": 5.0,
    "rate": 8.67,
    "baseRate": "SOFR",
    "maturity": "2030-12",
    "acq": null,
    "ccy": "USD",
    "pik": false
  },
  {
    "bdc": "TSLX",
    "entity": "Other Scorpio Bidco",
    "company": "Other Scorpio Bidco",
    "desc": null,
    "sector": null,
    "type": "First Lien",
    "affil": "",
    "fv": 2488.0,
    "cost": 2685.0,
    "par": null,
    "mark": 92.66,
    "spread": 5.75,
    "rate": 7.88,
    "baseRate": "EURIBOR",
    "maturity": "2031-04",
    "acq": null,
    "ccy": "EUR",
    "pik": false
  },
  {
    "bdc": "TSLX",
    "entity": "Other Sediver S.p.A",
    "company": "Other Sediver S.p.A",
    "desc": null,
    "sector": null,
    "type": "First Lien",
    "affil": "",
    "fv": 6343.0,
    "cost": 6733.0,
    "par": null,
    "mark": 94.21,
    "spread": 5.0,
    "rate": 7.13,
    "baseRate": "EURIBOR",
    "maturity": "2031-10",
    "acq": null,
    "ccy": "EUR",
    "pik": false
  },
  {
    "bdc": "TSLX",
    "entity": "Other Sediver S.p.A",
    "company": "Other Sediver S.p.A",
    "desc": null,
    "sector": null,
    "type": "First Lien",
    "affil": "",
    "fv": 14049.0,
    "cost": 13866.0,
    "par": null,
    "mark": 101.32,
    "spread": 5.0,
    "rate": 8.7,
    "baseRate": "SOFR",
    "maturity": "2031-10",
    "acq": null,
    "ccy": "USD",
    "pik": false
  },
  {
    "bdc": "TSLX",
    "entity": "Apellis Pharmaceuticals, Inc",
    "company": "Apellis Pharmaceuticals, Inc",
    "desc": null,
    "sector": "Pharmaceuticals",
    "type": "First Lien",
    "affil": "",
    "fv": 20428.0,
    "cost": 19737.0,
    "par": null,
    "mark": 103.5,
    "spread": 5.75,
    "rate": 9.45,
    "baseRate": "SOFR",
    "maturity": "2030-05",
    "acq": null,
    "ccy": "USD",
    "pik": false
  },
  {
    "bdc": "TSLX",
    "entity": "Arrowhead Pharmaceuticals, Inc",
    "company": "Arrowhead Pharmaceuticals, Inc",
    "desc": null,
    "sector": "Pharmaceuticals",
    "type": "First Lien",
    "affil": "",
    "fv": 29962.0,
    "cost": 26999.0,
    "par": null,
    "mark": 110.97,
    "spread": null,
    "rate": 15.0,
    "baseRate": null,
    "maturity": "2031-08",
    "acq": null,
    "ccy": "USD",
    "pik": false
  },
  {
    "bdc": "TSLX",
    "entity": "Elysium BidCo Limited",
    "company": "Elysium BidCo Limited",
    "desc": null,
    "sector": "Pharmaceuticals",
    "type": "First Lien",
    "affil": "",
    "fv": 39628.0,
    "cost": 45049.0,
    "par": null,
    "mark": 87.97,
    "spread": 7.25,
    "rate": 9.38,
    "baseRate": "EURIBOR",
    "maturity": "2030-12",
    "acq": null,
    "ccy": "EUR",
    "pik": false
  },
  {
    "bdc": "TSLX",
    "entity": "Elysium BidCo Limited",
    "company": "Elysium BidCo Limited",
    "desc": null,
    "sector": "Pharmaceuticals",
    "type": "First Lien",
    "affil": "",
    "fv": 9779.0,
    "cost": 12416.0,
    "par": null,
    "mark": 78.76,
    "spread": 7.25,
    "rate": 10.98,
    "baseRate": "SOFR",
    "maturity": "2030-12",
    "acq": null,
    "ccy": "GBP",
    "pik": false
  },
  {
    "bdc": "TSLX",
    "entity": "Cirrus (BidCo) Limited",
    "company": "Cirrus (BidCo) Limited",
    "desc": null,
    "sector": "Real Estate",
    "type": "First Lien",
    "affil": "",
    "fv": 690.0,
    "cost": 872.0,
    "par": null,
    "mark": 79.13,
    "spread": 5.25,
    "rate": 8.98,
    "baseRate": "SOFR",
    "maturity": "2030-08",
    "acq": null,
    "ccy": "GBP",
    "pik": false
  },
  {
    "bdc": "TSLX",
    "entity": "Acosta",
    "company": "Acosta",
    "desc": null,
    "sector": "Retail and Consumer Products",
    "type": "First Lien",
    "affil": "",
    "fv": 13483.0,
    "cost": 13606.0,
    "par": null,
    "mark": 99.1,
    "spread": 5.6,
    "rate": 9.22,
    "baseRate": "SOFR",
    "maturity": "2031-08",
    "acq": null,
    "ccy": "USD",
    "pik": false
  },
  {
    "bdc": "TSLX",
    "entity": "American Achievement, Corp",
    "company": "American Achievement, Corp",
    "desc": null,
    "sector": "Retail and Consumer Products",
    "type": "First Lien",
    "affil": "",
    "fv": 19626.0,
    "cost": 25796.0,
    "par": null,
    "mark": 76.08,
    "spread": 7.35,
    "rate": 11.02,
    "baseRate": "SOFR",
    "maturity": "2027-09",
    "acq": null,
    "ccy": "USD",
    "pik": true
  },
  {
    "bdc": "TSLX",
    "entity": "American Achievement, Corp",
    "company": "American Achievement, Corp",
    "desc": null,
    "sector": "Retail and Consumer Products",
    "type": "First Lien",
    "affil": "",
    "fv": 99.0,
    "cost": 1323.0,
    "par": null,
    "mark": 7.48,
    "spread": 15.1,
    "rate": 18.77,
    "baseRate": null,
    "maturity": "2027-09",
    "acq": null,
    "ccy": "USD",
    "pik": true
  },
  {
    "bdc": "TSLX",
    "entity": "American Achievement, Corp",
    "company": "American Achievement, Corp",
    "desc": null,
    "sector": "Retail and Consumer Products",
    "type": "Subordinated",
    "affil": "",
    "fv": 59.0,
    "cost": 545.0,
    "par": null,
    "mark": 10.83,
    "spread": 1.15,
    "rate": 4.81,
    "baseRate": "SOFR",
    "maturity": "2027-09",
    "acq": null,
    "ccy": "USD",
    "pik": false
  },
  {
    "bdc": "TSLX",
    "entity": "Bed Bath and Beyond Inc",
    "company": "Bed Bath and Beyond Inc",
    "desc": null,
    "sector": "Retail and Consumer Products",
    "type": "First Lien",
    "affil": "",
    "fv": 4684.0,
    "cost": 5851.0,
    "par": null,
    "mark": 80.05,
    "spread": 9.9,
    "rate": 13.57,
    "baseRate": "SOFR",
    "maturity": "2027-08",
    "acq": null,
    "ccy": "USD",
    "pik": false
  },
  {
    "bdc": "TSLX",
    "entity": "Bed Bath and Beyond Inc",
    "company": "Bed Bath and Beyond Inc",
    "desc": null,
    "sector": "Retail and Consumer Products",
    "type": "First Lien",
    "affil": "",
    "fv": 20015.0,
    "cost": 25255.0,
    "par": null,
    "mark": 79.25,
    "spread": 7.9,
    "rate": 11.57,
    "baseRate": "SOFR",
    "maturity": null,
    "acq": null,
    "ccy": "USD",
    "pik": false
  },
  {
    "bdc": "TSLX",
    "entity": "Bed Bath and Beyond Inc",
    "company": "Bed Bath and Beyond Inc",
    "desc": null,
    "sector": "Retail and Consumer Products",
    "type": "First Lien",
    "affil": "",
    "fv": 2833.0,
    "cost": 3575.0,
    "par": null,
    "mark": 79.24,
    "spread": 7.9,
    "rate": 11.57,
    "baseRate": "SOFR",
    "maturity": null,
    "acq": null,
    "ccy": "USD",
    "pik": false
  },
  {
    "bdc": "TSLX",
    "entity": "Belk, Inc",
    "company": "Belk, Inc",
    "desc": null,
    "sector": "Retail and Consumer Products",
    "type": "First Lien",
    "affil": "",
    "fv": 45806.0,
    "cost": 45331.0,
    "par": null,
    "mark": 101.05,
    "spread": 7.0,
    "rate": 10.67,
    "baseRate": "SOFR",
    "maturity": "2029-07",
    "acq": null,
    "ccy": "USD",
    "pik": false
  },
  {
    "bdc": "TSLX",
    "entity": "Blazing Star Parent, LLC",
    "company": "Blazing Star Parent, LLC",
    "desc": null,
    "sector": "Retail and Consumer Products",
    "type": "First Lien",
    "affil": "",
    "fv": 68434.0,
    "cost": 68201.0,
    "par": null,
    "mark": 100.34,
    "spread": 7.0,
    "rate": 10.67,
    "baseRate": "SOFR",
    "maturity": "2030-08",
    "acq": null,
    "ccy": "USD",
    "pik": false
  },
  {
    "bdc": "TSLX",
    "entity": "Cordance Operations, LLC",
    "company": "Cordance Operations, LLC",
    "desc": null,
    "sector": "Retail and Consumer Products",
    "type": "First Lien",
    "affil": "",
    "fv": 65187.0,
    "cost": 64759.0,
    "par": null,
    "mark": 100.66,
    "spread": 8.4,
    "rate": 12.07,
    "baseRate": "SOFR",
    "maturity": "2028-07",
    "acq": null,
    "ccy": "USD",
    "pik": false
  },
  {
    "bdc": "TSLX",
    "entity": "Neuintel, LLC",
    "company": "Neuintel, LLC",
    "desc": null,
    "sector": "Retail and Consumer Products",
    "type": "First Lien",
    "affil": "",
    "fv": 50697.0,
    "cost": 53454.0,
    "par": null,
    "mark": 94.84,
    "spread": 6.85,
    "rate": 10.52,
    "baseRate": "SOFR",
    "maturity": "2026-12",
    "acq": null,
    "ccy": "USD",
    "pik": false
  },
  {
    "bdc": "TSLX",
    "entity": "PDI TA Holdings, Inc",
    "company": "PDI TA Holdings, Inc",
    "desc": null,
    "sector": "Retail and Consumer Products",
    "type": "First Lien",
    "affil": "",
    "fv": 19777.0,
    "cost": 20012.0,
    "par": null,
    "mark": 98.83,
    "spread": 6.0,
    "rate": 9.67,
    "baseRate": "SOFR",
    "maturity": "2031-02",
    "acq": null,
    "ccy": "USD",
    "pik": true
  },
  {
    "bdc": "TSLX",
    "entity": "PDI TA Holdings, Inc",
    "company": "PDI TA Holdings, Inc",
    "desc": null,
    "sector": "Retail and Consumer Products",
    "type": "First Lien",
    "affil": "",
    "fv": 1494.0,
    "cost": 1514.0,
    "par": null,
    "mark": 98.68,
    "spread": 5.5,
    "rate": 9.17,
    "baseRate": "SOFR",
    "maturity": "2031-02",
    "acq": null,
    "ccy": "USD",
    "pik": false
  },
  {
    "bdc": "TSLX",
    "entity": "Rapid Data GmbH Unternehmensberatung",
    "company": "Rapid Data GmbH Unternehmensberatung",
    "desc": null,
    "sector": "Retail and Consumer Products",
    "type": "First Lien",
    "affil": "",
    "fv": 7401.0,
    "cost": 8137.0,
    "par": null,
    "mark": 90.95,
    "spread": 6.5,
    "rate": 8.52,
    "baseRate": "EURIBOR",
    "maturity": "2029-07",
    "acq": null,
    "ccy": "EUR",
    "pik": false
  },
  {
    "bdc": "TSLX",
    "entity": "Rapid Data GmbH Unternehmensberatung",
    "company": "Rapid Data GmbH Unternehmensberatung",
    "desc": null,
    "sector": "Retail and Consumer Products",
    "type": "First Lien",
    "affil": "",
    "fv": 316.0,
    "cost": 374.0,
    "par": null,
    "mark": 84.49,
    "spread": 6.5,
    "rate": 8.52,
    "baseRate": "EURIBOR",
    "maturity": "2029-06",
    "acq": null,
    "ccy": "EUR",
    "pik": false
  },
  {
    "bdc": "TSLX",
    "entity": "Tango Management Consulting, LLC",
    "company": "Tango Management Consulting, LLC",
    "desc": null,
    "sector": "Retail and Consumer Products",
    "type": "First Lien",
    "affil": "",
    "fv": 49280.0,
    "cost": 49881.0,
    "par": null,
    "mark": 98.8,
    "spread": 6.5,
    "rate": 10.16,
    "baseRate": "SOFR",
    "maturity": "2031-06",
    "acq": null,
    "ccy": "USD",
    "pik": false
  },
  {
    "bdc": "TSLX",
    "entity": "Ben Nevis Midco Limited",
    "company": "Ben Nevis Midco Limited",
    "desc": null,
    "sector": "Transportation",
    "type": "First Lien",
    "affil": "",
    "fv": 4988.0,
    "cost": 4967.0,
    "par": null,
    "mark": 100.42,
    "spread": 5.5,
    "rate": 9.17,
    "baseRate": "SOFR",
    "maturity": "2028-03",
    "acq": null,
    "ccy": "USD",
    "pik": false
  },
  {
    "bdc": "TSLX",
    "entity": "Marcura Equities LTD",
    "company": "Marcura Equities LTD",
    "desc": null,
    "sector": "Transportation",
    "type": "First Lien",
    "affil": "",
    "fv": 41752.0,
    "cost": 41339.0,
    "par": null,
    "mark": 101.0,
    "spread": 8.25,
    "rate": 11.98,
    "baseRate": "SOFR",
    "maturity": "2029-08",
    "acq": null,
    "ccy": "USD",
    "pik": true
  },
  {
    "bdc": "TSLX",
    "entity": "Marcura Equities LTD",
    "company": "Marcura Equities LTD",
    "desc": null,
    "sector": "Transportation",
    "type": "First Lien",
    "affil": "",
    "fv": 1113.0,
    "cost": 1394.0,
    "par": null,
    "mark": 79.84,
    "spread": 8.25,
    "rate": 11.98,
    "baseRate": "SOFR",
    "maturity": "2029-08",
    "acq": null,
    "ccy": "GBP",
    "pik": true
  },
  {
    "bdc": "TSLX",
    "entity": "Marcura Equities LTD",
    "company": "Marcura Equities LTD",
    "desc": null,
    "sector": "Transportation",
    "type": "First Lien",
    "affil": "",
    "fv": 1650.0,
    "cost": 1620.0,
    "par": null,
    "mark": 101.85,
    "spread": 7.5,
    "rate": 11.2,
    "baseRate": "SOFR",
    "maturity": "2029-08",
    "acq": null,
    "ccy": "USD",
    "pik": false
  },
  {
    "bdc": "TSLX",
    "entity": "Project44, Inc",
    "company": "Project44, Inc",
    "desc": null,
    "sector": "Transportation",
    "type": "First Lien",
    "affil": "",
    "fv": 53527.0,
    "cost": 53959.0,
    "par": null,
    "mark": 99.2,
    "spread": 6.35,
    "rate": 10.02,
    "baseRate": "SOFR",
    "maturity": "2027-11",
    "acq": null,
    "ccy": "USD",
    "pik": false
  },
  {
    "bdc": "TSLX",
    "entity": "Rail Acquisitions LLC",
    "company": "Rail Acquisitions LLC",
    "desc": null,
    "sector": "Transportation",
    "type": "First Lien",
    "affil": "",
    "fv": 22164.0,
    "cost": 22119.0,
    "par": null,
    "mark": 100.2,
    "spread": 6.0,
    "rate": 9.67,
    "baseRate": "SOFR",
    "maturity": "2030-01",
    "acq": null,
    "ccy": "USD",
    "pik": false
  },
  {
    "bdc": "TSLX",
    "entity": "Rail Acquisitions LLC",
    "company": "Rail Acquisitions LLC",
    "desc": null,
    "sector": "Transportation",
    "type": "Second Lien",
    "affil": "",
    "fv": 19516.0,
    "cost": 19139.0,
    "par": null,
    "mark": 101.97,
    "spread": null,
    "rate": 13.75,
    "baseRate": null,
    "maturity": "2031-01",
    "acq": null,
    "ccy": "USD",
    "pik": true
  },
  {
    "bdc": "TSLX",
    "entity": "Ranger Intermediate II, LLC",
    "company": "Ranger Intermediate II, LLC",
    "desc": null,
    "sector": "Transportation",
    "type": "First Lien",
    "affil": "",
    "fv": 68320.0,
    "cost": 68385.0,
    "par": null,
    "mark": 99.9,
    "spread": 5.5,
    "rate": 9.17,
    "baseRate": "SOFR",
    "maturity": "2030-01",
    "acq": null,
    "ccy": "USD",
    "pik": false
  },
  {
    "bdc": "TSLX",
    "entity": "Shiftmove GMBH",
    "company": "Shiftmove GMBH",
    "desc": null,
    "sector": "Transportation",
    "type": "First Lien",
    "affil": "",
    "fv": 36000.0,
    "cost": 40028.0,
    "par": null,
    "mark": 89.94,
    "spread": 6.0,
    "rate": 8.13,
    "baseRate": "EURIBOR",
    "maturity": "2030-09",
    "acq": null,
    "ccy": "EUR",
    "pik": false
  },
  {
    "bdc": "TSLX",
    "entity": "Artisan Topco LP",
    "company": "Artisan Topco LP",
    "desc": null,
    "sector": "Business Services",
    "type": "Preferred Equity",
    "affil": "",
    "fv": 1583.0,
    "cost": 2117.0,
    "par": null,
    "mark": 74.78,
    "spread": null,
    "rate": null,
    "baseRate": null,
    "maturity": null,
    "acq": null,
    "ccy": "USD",
    "pik": false
  },
  {
    "bdc": "TSLX",
    "entity": "Dye & Durham, Ltd",
    "company": "Dye & Durham, Ltd",
    "desc": null,
    "sector": "Business Services",
    "type": "Common Equity",
    "affil": "",
    "fv": 496.0,
    "cost": 3909.0,
    "par": null,
    "mark": 12.69,
    "spread": null,
    "rate": null,
    "baseRate": null,
    "maturity": null,
    "acq": null,
    "ccy": "CAD",
    "pik": false
  },
  {
    "bdc": "TSLX",
    "entity": "Insight Hideaway Aggregator, L.P",
    "company": "Insight Hideaway Aggregator, L.P",
    "desc": null,
    "sector": "Business Services",
    "type": "Equity",
    "affil": "",
    "fv": 3331.0,
    "cost": 3299.0,
    "par": null,
    "mark": 100.97,
    "spread": null,
    "rate": null,
    "baseRate": null,
    "maturity": null,
    "acq": null,
    "ccy": "USD",
    "pik": false
  },
  {
    "bdc": "TSLX",
    "entity": "Mitnick TA Aggregator, L.P",
    "company": "Mitnick TA Aggregator, L.P",
    "desc": null,
    "sector": "Business Services",
    "type": "Equity",
    "affil": "",
    "fv": 2087.0,
    "cost": 5249.0,
    "par": null,
    "mark": 39.76,
    "spread": null,
    "rate": null,
    "baseRate": null,
    "maturity": null,
    "acq": null,
    "ccy": "USD",
    "pik": false
  },
  {
    "bdc": "TSLX",
    "entity": "Newark FP Co-Invest, L.P",
    "company": "Newark FP Co-Invest, L.P",
    "desc": null,
    "sector": "Business Services",
    "type": "Equity",
    "affil": "",
    "fv": 1792.0,
    "cost": 2532.0,
    "par": null,
    "mark": 70.77,
    "spread": null,
    "rate": null,
    "baseRate": null,
    "maturity": null,
    "acq": null,
    "ccy": "USD",
    "pik": false
  },
  {
    "bdc": "TSLX",
    "entity": "Sprinklr, Inc",
    "company": "Sprinklr, Inc",
    "desc": null,
    "sector": "Business Services",
    "type": "Common Equity",
    "affil": "",
    "fv": 1701.0,
    "cost": 2445.0,
    "par": null,
    "mark": 69.57,
    "spread": null,
    "rate": null,
    "baseRate": null,
    "maturity": null,
    "acq": null,
    "ccy": "USD",
    "pik": false
  },
  {
    "bdc": "TSLX",
    "entity": "Warrior TopCo LP",
    "company": "Warrior TopCo LP",
    "desc": null,
    "sector": "Business Services",
    "type": "Equity",
    "affil": "",
    "fv": 598.0,
    "cost": 424.0,
    "par": null,
    "mark": 141.04,
    "spread": null,
    "rate": null,
    "baseRate": null,
    "maturity": null,
    "acq": null,
    "ccy": "USD",
    "pik": false
  },
  {
    "bdc": "TSLX",
    "entity": "Celtra Technologies, Inc",
    "company": "Celtra Technologies, Inc",
    "desc": null,
    "sector": "Communications",
    "type": "Equity",
    "affil": "",
    "fv": 1387.0,
    "cost": 1250.0,
    "par": null,
    "mark": 110.96,
    "spread": null,
    "rate": null,
    "baseRate": null,
    "maturity": null,
    "acq": null,
    "ccy": "USD",
    "pik": false
  },
  {
    "bdc": "TSLX",
    "entity": "IntelePeer Holdings, Inc",
    "company": "IntelePeer Holdings, Inc",
    "desc": null,
    "sector": "Communications",
    "type": "Preferred Equity",
    "affil": "",
    "fv": 141.0,
    "cost": 1816.0,
    "par": null,
    "mark": 7.76,
    "spread": null,
    "rate": null,
    "baseRate": null,
    "maturity": null,
    "acq": null,
    "ccy": "USD",
    "pik": false
  },
  {
    "bdc": "TSLX",
    "entity": "IntelePeer Holdings, Inc",
    "company": "IntelePeer Holdings, Inc",
    "desc": null,
    "sector": "Communications",
    "type": "Preferred Equity",
    "affil": "",
    "fv": 154.0,
    "cost": 2925.0,
    "par": null,
    "mark": 5.26,
    "spread": null,
    "rate": null,
    "baseRate": null,
    "maturity": null,
    "acq": null,
    "ccy": "USD",
    "pik": false
  },
  {
    "bdc": "TSLX",
    "entity": "Education EMS Linq, Inc",
    "company": "Education EMS Linq, Inc",
    "desc": null,
    "sector": null,
    "type": "Equity",
    "affil": "",
    "fv": 815.0,
    "cost": 5523.0,
    "par": null,
    "mark": 14.76,
    "spread": null,
    "rate": null,
    "baseRate": null,
    "maturity": null,
    "acq": null,
    "ccy": "USD",
    "pik": false
  },
  {
    "bdc": "TSLX",
    "entity": "AF Eagle Parent, L.P",
    "company": "AF Eagle Parent, L.P",
    "desc": null,
    "sector": "Financial Services",
    "type": "Equity",
    "affil": "",
    "fv": 3815.0,
    "cost": 4091.0,
    "par": null,
    "mark": 93.25,
    "spread": null,
    "rate": null,
    "baseRate": null,
    "maturity": null,
    "acq": null,
    "ccy": "USD",
    "pik": false
  },
  {
    "bdc": "TSLX",
    "entity": "Newport Parent Holdings, L.P",
    "company": "Newport Parent Holdings, L.P",
    "desc": null,
    "sector": "Financial Services",
    "type": "Equity",
    "affil": "",
    "fv": 11027.0,
    "cost": 4177.0,
    "par": null,
    "mark": 263.99,
    "spread": null,
    "rate": null,
    "baseRate": null,
    "maturity": null,
    "acq": null,
    "ccy": "USD",
    "pik": false
  },
  {
    "bdc": "TSLX",
    "entity": "Oxford Square Capital Corp",
    "company": "Oxford Square Capital Corp",
    "desc": null,
    "sector": "Financial Services",
    "type": "Common Equity",
    "affil": "",
    "fv": 3.0,
    "cost": 6.0,
    "par": null,
    "mark": 50.0,
    "spread": null,
    "rate": null,
    "baseRate": null,
    "maturity": null,
    "acq": null,
    "ccy": "USD",
    "pik": false
  },
  {
    "bdc": "TSLX",
    "entity": "Passport Labs, Inc",
    "company": "Passport Labs, Inc",
    "desc": null,
    "sector": "Financial Services",
    "type": "Warrant",
    "affil": "",
    "fv": 1223.0,
    "cost": 192.0,
    "par": null,
    "mark": 636.98,
    "spread": null,
    "rate": null,
    "baseRate": null,
    "maturity": null,
    "acq": null,
    "ccy": "USD",
    "pik": false
  },
  {
    "bdc": "TSLX",
    "entity": "TS Imagine, Inc",
    "company": "TS Imagine, Inc",
    "desc": null,
    "sector": "Financial Services",
    "type": "Equity",
    "affil": "",
    "fv": 611.0,
    "cost": 600.0,
    "par": null,
    "mark": 101.83,
    "spread": null,
    "rate": null,
    "baseRate": null,
    "maturity": null,
    "acq": null,
    "ccy": "USD",
    "pik": false
  },
  {
    "bdc": "TSLX",
    "entity": "TS Imagine, Inc",
    "company": "TS Imagine, Inc",
    "desc": null,
    "sector": "Financial Services",
    "type": "Equity",
    "affil": "",
    "fv": 45.0,
    "cost": 46.0,
    "par": null,
    "mark": 97.83,
    "spread": null,
    "rate": 20.0,
    "baseRate": null,
    "maturity": null,
    "acq": null,
    "ccy": "USD",
    "pik": false
  },
  {
    "bdc": "TSLX",
    "entity": "Caris Life Sciences, Inc",
    "company": "Caris Life Sciences, Inc",
    "desc": null,
    "sector": "Healthcare",
    "type": "Common Equity",
    "affil": "",
    "fv": 12767.0,
    "cost": 8254.0,
    "par": null,
    "mark": 154.68,
    "spread": null,
    "rate": null,
    "baseRate": null,
    "maturity": null,
    "acq": null,
    "ccy": "USD",
    "pik": false
  },
  {
    "bdc": "TSLX",
    "entity": "Merative Topco L.P",
    "company": "Merative Topco L.P",
    "desc": null,
    "sector": "Healthcare",
    "type": "Equity",
    "affil": "",
    "fv": 13880.0,
    "cost": 9897.0,
    "par": null,
    "mark": 140.24,
    "spread": null,
    "rate": null,
    "baseRate": null,
    "maturity": null,
    "acq": null,
    "ccy": "USD",
    "pik": false
  },
  {
    "bdc": "TSLX",
    "entity": "Raptor US Buyer II Corp",
    "company": "Raptor US Buyer II Corp",
    "desc": null,
    "sector": "Healthcare",
    "type": "Equity",
    "affil": "",
    "fv": 2150.0,
    "cost": 2033.0,
    "par": null,
    "mark": 105.76,
    "spread": null,
    "rate": null,
    "baseRate": null,
    "maturity": null,
    "acq": null,
    "ccy": "USD",
    "pik": false
  },
  {
    "bdc": "TSLX",
    "entity": "IRGSE Holding Corp",
    "company": "IRGSE Holding Corp",
    "desc": null,
    "sector": "Hotel, Gaming and Leisure",
    "type": "Equity",
    "affil": "",
    "fv": 125.0,
    "cost": 21883.0,
    "par": null,
    "mark": 0.57,
    "spread": null,
    "rate": null,
    "baseRate": null,
    "maturity": null,
    "acq": null,
    "ccy": "USD",
    "pik": false
  },
  {
    "bdc": "TSLX",
    "entity": "IRGSE Holding Corp",
    "company": "IRGSE Holding Corp",
    "desc": null,
    "sector": "Hotel, Gaming and Leisure",
    "type": "Equity",
    "affil": "",
    "fv": 43.0,
    "cost": 100.0,
    "par": null,
    "mark": 43.0,
    "spread": null,
    "rate": null,
    "baseRate": null,
    "maturity": null,
    "acq": null,
    "ccy": "USD",
    "pik": false
  },
  {
    "bdc": "TSLX",
    "entity": "Axonify, Inc",
    "company": "Axonify, Inc",
    "desc": null,
    "sector": "Human Resource Support Services",
    "type": "Equity",
    "affil": "",
    "fv": 2325.0,
    "cost": 3780.0,
    "par": null,
    "mark": 61.51,
    "spread": null,
    "rate": null,
    "baseRate": null,
    "maturity": null,
    "acq": null,
    "ccy": "USD",
    "pik": false
  },
  {
    "bdc": "TSLX",
    "entity": "bswift, LLC",
    "company": "bswift, LLC",
    "desc": null,
    "sector": "Human Resource Support Services",
    "type": "Equity",
    "affil": "",
    "fv": 3351.0,
    "cost": 2394.0,
    "par": null,
    "mark": 139.97,
    "spread": null,
    "rate": null,
    "baseRate": null,
    "maturity": null,
    "acq": null,
    "ccy": "USD",
    "pik": false
  },
  {
    "bdc": "TSLX",
    "entity": "DaySmart Holdings, LLC",
    "company": "DaySmart Holdings, LLC",
    "desc": null,
    "sector": "Human Resource Support Services",
    "type": "Equity",
    "affil": "",
    "fv": 1747.0,
    "cost": 1347.0,
    "par": null,
    "mark": 129.7,
    "spread": null,
    "rate": null,
    "baseRate": null,
    "maturity": null,
    "acq": null,
    "ccy": "USD",
    "pik": false
  },
  {
    "bdc": "TSLX",
    "entity": "Employment Hero Holdings Pty Ltd",
    "company": "Employment Hero Holdings Pty Ltd",
    "desc": null,
    "sector": "Human Resource Support Services",
    "type": "Preferred Equity",
    "affil": "",
    "fv": 5970.0,
    "cost": 2134.0,
    "par": null,
    "mark": 279.76,
    "spread": null,
    "rate": null,
    "baseRate": null,
    "maturity": null,
    "acq": null,
    "ccy": "AUD",
    "pik": false
  },
  {
    "bdc": "TSLX",
    "entity": "Bayshore Intermediate #2, L.P. Co-Invest",
    "company": "Bayshore Intermediate #2, L.P. Co-Invest",
    "desc": null,
    "sector": "Internet Services",
    "type": "Common Equity",
    "affil": "",
    "fv": 12526.0,
    "cost": 8837.0,
    "par": null,
    "mark": 141.74,
    "spread": null,
    "rate": null,
    "baseRate": null,
    "maturity": null,
    "acq": null,
    "ccy": "USD",
    "pik": false
  },
  {
    "bdc": "TSLX",
    "entity": "Bayshore Intermediate #2, L.P. Co-Invest 2",
    "company": "Bayshore Intermediate #2, L.P. Co-Invest 2",
    "desc": null,
    "sector": "Internet Services",
    "type": "Common Equity",
    "affil": "",
    "fv": 4952.0,
    "cost": 3494.0,
    "par": null,
    "mark": 141.73,
    "spread": null,
    "rate": null,
    "baseRate": null,
    "maturity": null,
    "acq": null,
    "ccy": "USD",
    "pik": false
  },
  {
    "bdc": "TSLX",
    "entity": "Bigtincan Holdings L.P",
    "company": "Bigtincan Holdings L.P",
    "desc": null,
    "sector": "Internet Services",
    "type": "Equity",
    "affil": "",
    "fv": 2786.0,
    "cost": 3019.0,
    "par": null,
    "mark": 92.28,
    "spread": null,
    "rate": null,
    "baseRate": null,
    "maturity": null,
    "acq": null,
    "ccy": "USD",
    "pik": false
  },
  {
    "bdc": "TSLX",
    "entity": "Khoros, LLC",
    "company": "Khoros, LLC",
    "desc": null,
    "sector": "Internet Services",
    "type": "Equity",
    "affil": "",
    "fv": 7176.0,
    "cost": 7614.0,
    "par": null,
    "mark": 94.25,
    "spread": null,
    "rate": null,
    "baseRate": null,
    "maturity": null,
    "acq": null,
    "ccy": "USD",
    "pik": false
  },
  {
    "bdc": "TSLX",
    "entity": "Lucidworks, Inc",
    "company": "Lucidworks, Inc",
    "desc": null,
    "sector": "Internet Services",
    "type": "Preferred Equity",
    "affil": "",
    "fv": 454.0,
    "cost": 800.0,
    "par": null,
    "mark": 56.75,
    "spread": null,
    "rate": null,
    "baseRate": null,
    "maturity": null,
    "acq": null,
    "ccy": "USD",
    "pik": false
  },
  {
    "bdc": "TSLX",
    "entity": "Piano Software, Inc",
    "company": "Piano Software, Inc",
    "desc": null,
    "sector": "Internet Services",
    "type": "Preferred Equity",
    "affil": "",
    "fv": 2400.0,
    "cost": 3000.0,
    "par": null,
    "mark": 80.0,
    "spread": null,
    "rate": null,
    "baseRate": null,
    "maturity": null,
    "acq": null,
    "ccy": "USD",
    "pik": false
  },
  {
    "bdc": "TSLX",
    "entity": "Piano Software, Inc",
    "company": "Piano Software, Inc",
    "desc": null,
    "sector": "Internet Services",
    "type": "Preferred Equity",
    "affil": "",
    "fv": 316.0,
    "cost": 198.0,
    "par": null,
    "mark": 159.6,
    "spread": null,
    "rate": null,
    "baseRate": null,
    "maturity": null,
    "acq": null,
    "ccy": "USD",
    "pik": false
  },
  {
    "bdc": "TSLX",
    "entity": "SMA Technologies Holdings, LLC",
    "company": "SMA Technologies Holdings, LLC",
    "desc": null,
    "sector": "Internet Services",
    "type": "Equity",
    "affil": "",
    "fv": 2297.0,
    "cost": 1584.0,
    "par": null,
    "mark": 145.01,
    "spread": null,
    "rate": null,
    "baseRate": null,
    "maturity": null,
    "acq": null,
    "ccy": "USD",
    "pik": false
  },
  {
    "bdc": "TSLX",
    "entity": "SMA Technologies Holdings, LLC",
    "company": "SMA Technologies Holdings, LLC",
    "desc": null,
    "sector": "Internet Services",
    "type": "Equity",
    "affil": "",
    "fv": 99.0,
    "cost": 68.0,
    "par": null,
    "mark": 145.59,
    "spread": null,
    "rate": null,
    "baseRate": null,
    "maturity": null,
    "acq": null,
    "ccy": "USD",
    "pik": false
  },
  {
    "bdc": "TSLX",
    "entity": "Validity, Inc",
    "company": "Validity, Inc",
    "desc": null,
    "sector": "Marketing Services",
    "type": "Preferred Equity",
    "affil": "",
    "fv": 9024.0,
    "cost": 3840.0,
    "par": null,
    "mark": 235.0,
    "spread": null,
    "rate": null,
    "baseRate": null,
    "maturity": null,
    "acq": null,
    "ccy": "USD",
    "pik": false
  },
  {
    "bdc": "TSLX",
    "entity": "TRP Assets, LLC",
    "company": "TRP Assets, LLC",
    "desc": null,
    "sector": "Oil, Gas and Consumable Fuels",
    "type": "Equity",
    "affil": "",
    "fv": 11916.0,
    "cost": 8926.0,
    "par": null,
    "mark": 133.5,
    "spread": null,
    "rate": null,
    "baseRate": null,
    "maturity": null,
    "acq": null,
    "ccy": "USD",
    "pik": false
  },
  {
    "bdc": "TSLX",
    "entity": "TherapeuticsMD, Inc",
    "company": "TherapeuticsMD, Inc",
    "desc": null,
    "sector": "Pharmaceuticals",
    "type": "Warrant",
    "affil": "",
    "fv": null,
    "cost": 1029.0,
    "par": null,
    "mark": null,
    "spread": null,
    "rate": null,
    "baseRate": null,
    "maturity": null,
    "acq": null,
    "ccy": "USD",
    "pik": false
  },
  {
    "bdc": "TSLX",
    "entity": "Elysium BidCo Limited",
    "company": "Elysium BidCo Limited",
    "desc": null,
    "sector": "Pharmaceuticals",
    "type": "Equity",
    "affil": "",
    "fv": 5225.0,
    "cost": 6341.0,
    "par": null,
    "mark": 82.4,
    "spread": null,
    "rate": null,
    "baseRate": null,
    "maturity": null,
    "acq": null,
    "ccy": "GBP",
    "pik": false
  },
  {
    "bdc": "TSLX",
    "entity": "American Achievement, Corp",
    "company": "American Achievement, Corp",
    "desc": null,
    "sector": "Retail and Consumer Products",
    "type": "Equity",
    "affil": "",
    "fv": 50.0,
    "cost": null,
    "par": null,
    "mark": null,
    "spread": null,
    "rate": null,
    "baseRate": null,
    "maturity": null,
    "acq": null,
    "ccy": "USD",
    "pik": false
  },
  {
    "bdc": "TSLX",
    "entity": "Copper Bidco, LLC",
    "company": "Copper Bidco, LLC",
    "desc": null,
    "sector": "Retail and Consumer Products",
    "type": "Equity",
    "affil": "",
    "fv": 10767.0,
    "cost": 1083.0,
    "par": null,
    "mark": 994.18,
    "spread": null,
    "rate": null,
    "baseRate": null,
    "maturity": null,
    "acq": null,
    "ccy": "USD",
    "pik": false
  },
  {
    "bdc": "TSLX",
    "entity": "Neuintel, LLC",
    "company": "Neuintel, LLC",
    "desc": null,
    "sector": "Retail and Consumer Products",
    "type": "Equity",
    "affil": "",
    "fv": 60.0,
    "cost": 3000.0,
    "par": null,
    "mark": 2.0,
    "spread": null,
    "rate": null,
    "baseRate": null,
    "maturity": null,
    "acq": null,
    "ccy": "USD",
    "pik": false
  },
  {
    "bdc": "TSLX",
    "entity": "RailTrac Holdings Inc",
    "company": "RailTrac Holdings Inc",
    "desc": null,
    "sector": "Transportation",
    "type": "Warrant",
    "affil": "",
    "fv": 2717.0,
    "cost": 2717.0,
    "par": null,
    "mark": 100.0,
    "spread": null,
    "rate": null,
    "baseRate": null,
    "maturity": null,
    "acq": null,
    "ccy": "USD",
    "pik": false
  },
  {
    "bdc": "TSLX",
    "entity": "Ranger Parent I, Inc",
    "company": "Ranger Parent I, Inc",
    "desc": null,
    "sector": "Transportation",
    "type": "Preferred Equity",
    "affil": "",
    "fv": 5103.0,
    "cost": 5362.0,
    "par": null,
    "mark": 95.17,
    "spread": null,
    "rate": 14.5,
    "baseRate": null,
    "maturity": null,
    "acq": null,
    "ccy": "USD",
    "pik": true
  },
  {
    "bdc": "TSLX",
    "entity": "Ranger Parent I, Inc",
    "company": "Ranger Parent I, Inc",
    "desc": null,
    "sector": "Transportation",
    "type": "Warrant",
    "affil": "",
    "fv": 312.0,
    "cost": 312.0,
    "par": null,
    "mark": 100.0,
    "spread": null,
    "rate": null,
    "baseRate": null,
    "maturity": null,
    "acq": null,
    "ccy": "USD",
    "pik": false
  },
  {
    "bdc": "TSLX",
    "entity": "Apidos CLO",
    "company": "Apidos CLO",
    "desc": null,
    "sector": null,
    "type": "Structured Credit",
    "affil": "",
    "fv": 3931.0,
    "cost": 4015.0,
    "par": null,
    "mark": 97.91,
    "spread": 5.2,
    "rate": 8.87,
    "baseRate": "SOFR",
    "maturity": "2033-04",
    "acq": null,
    "ccy": "USD",
    "pik": false
  },
  {
    "bdc": "TSLX",
    "entity": "Ares CLO Ltd",
    "company": "Ares CLO Ltd",
    "desc": null,
    "sector": null,
    "type": "Structured Credit",
    "affil": "",
    "fv": 2325.0,
    "cost": 2523.0,
    "par": null,
    "mark": 92.15,
    "spread": 6.0,
    "rate": 9.67,
    "baseRate": "SOFR",
    "maturity": "2038-10",
    "acq": null,
    "ccy": "USD",
    "pik": false
  },
  {
    "bdc": "TSLX",
    "entity": "Ares CLO Ltd",
    "company": "Ares CLO Ltd",
    "desc": null,
    "sector": null,
    "type": "Structured Credit",
    "affil": "",
    "fv": 1912.0,
    "cost": 2043.0,
    "par": null,
    "mark": 93.59,
    "spread": 6.5,
    "rate": 10.17,
    "baseRate": "SOFR",
    "maturity": "2039-10",
    "acq": null,
    "ccy": "USD",
    "pik": false
  },
  {
    "bdc": "TSLX",
    "entity": "Ares CLO Ltd",
    "company": "Ares CLO Ltd",
    "desc": null,
    "sector": null,
    "type": "Structured Credit",
    "affil": "",
    "fv": 3255.0,
    "cost": 3545.0,
    "par": null,
    "mark": 91.82,
    "spread": 6.0,
    "rate": 9.67,
    "baseRate": "SOFR",
    "maturity": "2036-07",
    "acq": null,
    "ccy": "USD",
    "pik": false
  },
  {
    "bdc": "TSLX",
    "entity": "Benefit Street Partners CLO Ltd",
    "company": "Benefit Street Partners CLO Ltd",
    "desc": null,
    "sector": null,
    "type": "Structured Credit",
    "affil": "",
    "fv": 1670.0,
    "cost": 1725.0,
    "par": null,
    "mark": 96.81,
    "spread": 4.5,
    "rate": 8.17,
    "baseRate": "SOFR",
    "maturity": "2038-04",
    "acq": null,
    "ccy": "USD",
    "pik": false
  },
  {
    "bdc": "TSLX",
    "entity": "Birch Grove CLO Ltd",
    "company": "Birch Grove CLO Ltd",
    "desc": null,
    "sector": null,
    "type": "Structured Credit",
    "affil": "",
    "fv": 1250.0,
    "cost": 1268.0,
    "par": null,
    "mark": 98.58,
    "spread": 6.65,
    "rate": 10.32,
    "baseRate": "SOFR",
    "maturity": "2037-07",
    "acq": null,
    "ccy": "USD",
    "pik": false
  },
  {
    "bdc": "TSLX",
    "entity": "Canyon CLO Ltd",
    "company": "Canyon CLO Ltd",
    "desc": null,
    "sector": null,
    "type": "Structured Credit",
    "affil": "",
    "fv": 1090.0,
    "cost": 1118.0,
    "par": null,
    "mark": 97.5,
    "spread": 4.75,
    "rate": 8.42,
    "baseRate": "SOFR",
    "maturity": "2038-04",
    "acq": null,
    "ccy": "USD",
    "pik": false
  },
  {
    "bdc": "TSLX",
    "entity": "Carlyle US CLO Ltd",
    "company": "Carlyle US CLO Ltd",
    "desc": null,
    "sector": null,
    "type": "Structured Credit",
    "affil": "",
    "fv": 2394.0,
    "cost": 2546.0,
    "par": null,
    "mark": 94.03,
    "spread": 7.56,
    "rate": 11.23,
    "baseRate": "SOFR",
    "maturity": "2037-07",
    "acq": null,
    "ccy": "USD",
    "pik": false
  },
  {
    "bdc": "TSLX",
    "entity": "Carlyle US CLO Ltd",
    "company": "Carlyle US CLO Ltd",
    "desc": null,
    "sector": null,
    "type": "Structured Credit",
    "affil": "",
    "fv": 3134.0,
    "cost": 3321.0,
    "par": null,
    "mark": 94.37,
    "spread": 7.3,
    "rate": 10.97,
    "baseRate": "SOFR",
    "maturity": "2040-01",
    "acq": null,
    "ccy": "USD",
    "pik": false
  },
  {
    "bdc": "TSLX",
    "entity": "CarVal CLO Ltd",
    "company": "CarVal CLO Ltd",
    "desc": null,
    "sector": null,
    "type": "Structured Credit",
    "affil": "",
    "fv": 1853.0,
    "cost": 2013.0,
    "par": null,
    "mark": 92.05,
    "spread": 7.01,
    "rate": 10.68,
    "baseRate": "SOFR",
    "maturity": "2034-10",
    "acq": null,
    "ccy": "USD",
    "pik": false
  },
  {
    "bdc": "TSLX",
    "entity": "CarVal CLO Ltd",
    "company": "CarVal CLO Ltd",
    "desc": null,
    "sector": null,
    "type": "Structured Credit",
    "affil": "",
    "fv": 2805.0,
    "cost": 3030.0,
    "par": null,
    "mark": 92.57,
    "spread": 6.35,
    "rate": 10.02,
    "baseRate": "SOFR",
    "maturity": "2037-07",
    "acq": null,
    "ccy": "USD",
    "pik": false
  },
  {
    "bdc": "TSLX",
    "entity": "CIFC Funding Ltd",
    "company": "CIFC Funding Ltd",
    "desc": null,
    "sector": null,
    "type": "Structured Credit",
    "affil": "",
    "fv": 3856.0,
    "cost": 4026.0,
    "par": null,
    "mark": 95.78,
    "spread": 4.9,
    "rate": 8.57,
    "baseRate": "SOFR",
    "maturity": "2040-01",
    "acq": null,
    "ccy": "USD",
    "pik": false
  },
  {
    "bdc": "TSLX",
    "entity": "CIFC Funding Ltd",
    "company": "CIFC Funding Ltd",
    "desc": null,
    "sector": null,
    "type": "Structured Credit",
    "affil": "",
    "fv": 2684.0,
    "cost": 2809.0,
    "par": null,
    "mark": 95.55,
    "spread": 4.9,
    "rate": 8.57,
    "baseRate": "SOFR",
    "maturity": "2035-01",
    "acq": null,
    "ccy": "USD",
    "pik": false
  },
  {
    "bdc": "TSLX",
    "entity": "CIFC Funding Ltd",
    "company": "CIFC Funding Ltd",
    "desc": null,
    "sector": null,
    "type": "Structured Credit",
    "affil": "",
    "fv": 2873.0,
    "cost": 3008.0,
    "par": null,
    "mark": 95.51,
    "spread": 5.25,
    "rate": 8.92,
    "baseRate": "SOFR",
    "maturity": "2035-07",
    "acq": null,
    "ccy": "USD",
    "pik": false
  },
  {
    "bdc": "TSLX",
    "entity": "Diameter Capital CLO Ltd",
    "company": "Diameter Capital CLO Ltd",
    "desc": null,
    "sector": null,
    "type": "Structured Credit",
    "affil": "",
    "fv": 3407.0,
    "cost": 3530.0,
    "par": null,
    "mark": 96.52,
    "spread": 4.7,
    "rate": 8.37,
    "baseRate": "SOFR",
    "maturity": "2038-04",
    "acq": null,
    "ccy": "USD",
    "pik": false
  },
  {
    "bdc": "TSLX",
    "entity": "Goldentree Loan Management US CLO Ltd",
    "company": "Goldentree Loan Management US CLO Ltd",
    "desc": null,
    "sector": null,
    "type": "Structured Credit",
    "affil": "",
    "fv": 4843.0,
    "cost": 4974.0,
    "par": null,
    "mark": 97.37,
    "spread": 4.5,
    "rate": 8.17,
    "baseRate": "SOFR",
    "maturity": "2038-01",
    "acq": null,
    "ccy": "USD",
    "pik": false
  },
  {
    "bdc": "TSLX",
    "entity": "Goldentree Loan Management US CLO Ltd",
    "company": "Goldentree Loan Management US CLO Ltd",
    "desc": null,
    "sector": null,
    "type": "Structured Credit",
    "affil": "",
    "fv": 2942.0,
    "cost": 3021.0,
    "par": null,
    "mark": 97.38,
    "spread": 5.4,
    "rate": 9.07,
    "baseRate": "SOFR",
    "maturity": "2039-01",
    "acq": null,
    "ccy": "USD",
    "pik": false
  },
  {
    "bdc": "TSLX",
    "entity": "Lake George Park CLO Ltd",
    "company": "Lake George Park CLO Ltd",
    "desc": null,
    "sector": null,
    "type": "Structured Credit",
    "affil": "",
    "fv": 4357.0,
    "cost": 4500.0,
    "par": null,
    "mark": 96.82,
    "spread": 4.6,
    "rate": 8.27,
    "baseRate": "SOFR",
    "maturity": "2038-04",
    "acq": null,
    "ccy": "USD",
    "pik": false
  },
  {
    "bdc": "TSLX",
    "entity": "Madison Park Funding Ltd",
    "company": "Madison Park Funding Ltd",
    "desc": null,
    "sector": null,
    "type": "Structured Credit",
    "affil": "",
    "fv": 4219.0,
    "cost": 4408.0,
    "par": null,
    "mark": 95.71,
    "spread": 5.0,
    "rate": 8.67,
    "baseRate": "SOFR",
    "maturity": "2038-07",
    "acq": null,
    "ccy": "USD",
    "pik": false
  },
  {
    "bdc": "TSLX",
    "entity": "Madison Park Funding Ltd",
    "company": "Madison Park Funding Ltd",
    "desc": null,
    "sector": null,
    "type": "Structured Credit",
    "affil": "",
    "fv": 4359.0,
    "cost": 4550.0,
    "par": null,
    "mark": 95.8,
    "spread": 5.25,
    "rate": 8.92,
    "baseRate": "SOFR",
    "maturity": "2038-07",
    "acq": null,
    "ccy": "USD",
    "pik": false
  },
  {
    "bdc": "TSLX",
    "entity": "Neuberger Berman CLO Ltd",
    "company": "Neuberger Berman CLO Ltd",
    "desc": null,
    "sector": null,
    "type": "Structured Credit",
    "affil": "",
    "fv": 3859.0,
    "cost": 4009.0,
    "par": null,
    "mark": 96.26,
    "spread": 4.9,
    "rate": 8.57,
    "baseRate": "SOFR",
    "maturity": "2039-04",
    "acq": null,
    "ccy": "USD",
    "pik": false
  },
  {
    "bdc": "TSLX",
    "entity": "Neuberger Berman CLO Ltd",
    "company": "Neuberger Berman CLO Ltd",
    "desc": null,
    "sector": null,
    "type": "Structured Credit",
    "affil": "",
    "fv": 1113.0,
    "cost": 1151.0,
    "par": null,
    "mark": 96.7,
    "spread": 4.75,
    "rate": 8.42,
    "baseRate": "SOFR",
    "maturity": "2039-04",
    "acq": null,
    "ccy": "USD",
    "pik": false
  },
  {
    "bdc": "TSLX",
    "entity": "Neuberger Berman Loan Advisers CLO Ltd",
    "company": "Neuberger Berman Loan Advisers CLO Ltd",
    "desc": null,
    "sector": null,
    "type": "Structured Credit",
    "affil": "",
    "fv": 961.0,
    "cost": 1024.0,
    "par": null,
    "mark": 93.85,
    "spread": 7.0,
    "rate": 10.67,
    "baseRate": "SOFR",
    "maturity": "2038-10",
    "acq": null,
    "ccy": "USD",
    "pik": false
  },
  {
    "bdc": "TSLX",
    "entity": "Neuberger Berman Loan Advisers CLO Ltd",
    "company": "Neuberger Berman Loan Advisers CLO Ltd",
    "desc": null,
    "sector": null,
    "type": "Structured Credit",
    "affil": "",
    "fv": 1955.0,
    "cost": 2029.0,
    "par": null,
    "mark": 96.35,
    "spread": 5.5,
    "rate": 9.17,
    "baseRate": "SOFR",
    "maturity": "2039-04",
    "acq": null,
    "ccy": "USD",
    "pik": false
  },
  {
    "bdc": "TSLX",
    "entity": "Neuberger Berman Loan Advisers CLO Ltd",
    "company": "Neuberger Berman Loan Advisers CLO Ltd",
    "desc": null,
    "sector": null,
    "type": "Structured Credit",
    "affil": "",
    "fv": 956.0,
    "cost": 1006.0,
    "par": null,
    "mark": 95.03,
    "spread": 5.15,
    "rate": 8.82,
    "baseRate": "SOFR",
    "maturity": "2035-10",
    "acq": null,
    "ccy": "USD",
    "pik": false
  },
  {
    "bdc": "TSLX",
    "entity": "Oaktree CLO Ltd",
    "company": "Oaktree CLO Ltd",
    "desc": null,
    "sector": null,
    "type": "Structured Credit",
    "affil": "",
    "fv": 3411.0,
    "cost": 3541.0,
    "par": null,
    "mark": 96.33,
    "spread": 6.4,
    "rate": 10.07,
    "baseRate": "SOFR",
    "maturity": "2037-10",
    "acq": null,
    "ccy": "USD",
    "pik": false
  },
  {
    "bdc": "TSLX",
    "entity": "Octagon 67 Ltd",
    "company": "Octagon 67 Ltd",
    "desc": null,
    "sector": null,
    "type": "Structured Credit",
    "affil": "",
    "fv": 2896.0,
    "cost": 3100.0,
    "par": null,
    "mark": 93.42,
    "spread": 7.41,
    "rate": 11.08,
    "baseRate": "SOFR",
    "maturity": "2038-07",
    "acq": null,
    "ccy": "USD",
    "pik": false
  },
  {
    "bdc": "TSLX",
    "entity": "Oha Credit Funding Ltd",
    "company": "Oha Credit Funding Ltd",
    "desc": null,
    "sector": null,
    "type": "Structured Credit",
    "affil": "",
    "fv": 1234.0,
    "cost": 1271.0,
    "par": null,
    "mark": 97.09,
    "spread": 5.55,
    "rate": 9.22,
    "baseRate": "SOFR",
    "maturity": "2038-07",
    "acq": null,
    "ccy": "USD",
    "pik": false
  },
  {
    "bdc": "TSLX",
    "entity": "Palmer Square CLO Ltd",
    "company": "Palmer Square CLO Ltd",
    "desc": null,
    "sector": null,
    "type": "Structured Credit",
    "affil": "",
    "fv": 3722.0,
    "cost": 4036.0,
    "par": null,
    "mark": 92.22,
    "spread": 5.75,
    "rate": 9.42,
    "baseRate": "SOFR",
    "maturity": "2038-07",
    "acq": null,
    "ccy": "USD",
    "pik": false
  },
  {
    "bdc": "TSLX",
    "entity": "Palmer Square CLO Ltd",
    "company": "Palmer Square CLO Ltd",
    "desc": null,
    "sector": null,
    "type": "Structured Credit",
    "affil": "",
    "fv": 2178.0,
    "cost": 2251.0,
    "par": null,
    "mark": 96.76,
    "spread": 4.5,
    "rate": 8.17,
    "baseRate": "SOFR",
    "maturity": "2038-04",
    "acq": null,
    "ccy": "USD",
    "pik": false
  },
  {
    "bdc": "TSLX",
    "entity": "Pikes Peak CLO Ltd",
    "company": "Pikes Peak CLO Ltd",
    "desc": null,
    "sector": null,
    "type": "Structured Credit",
    "affil": "",
    "fv": 2832.0,
    "cost": 3066.0,
    "par": null,
    "mark": 92.37,
    "spread": 6.0,
    "rate": 9.67,
    "baseRate": "SOFR",
    "maturity": "2038-07",
    "acq": null,
    "ccy": "USD",
    "pik": false
  },
  {
    "bdc": "TSLX",
    "entity": "Regatta Funding Ltd",
    "company": "Regatta Funding Ltd",
    "desc": null,
    "sector": null,
    "type": "Structured Credit",
    "affil": "",
    "fv": 964.0,
    "cost": 1019.0,
    "par": null,
    "mark": 94.6,
    "spread": 6.5,
    "rate": 10.17,
    "baseRate": "SOFR",
    "maturity": "2037-10",
    "acq": null,
    "ccy": "USD",
    "pik": false
  },
  {
    "bdc": "TSLX",
    "entity": "Riverbank Park CLO Ltd",
    "company": "Riverbank Park CLO Ltd",
    "desc": null,
    "sector": null,
    "type": "Structured Credit",
    "affil": "",
    "fv": 4121.0,
    "cost": 4528.0,
    "par": null,
    "mark": 91.01,
    "spread": 4.8,
    "rate": 8.47,
    "baseRate": "SOFR",
    "maturity": "2038-01",
    "acq": null,
    "ccy": "USD",
    "pik": false
  },
  {
    "bdc": "TSLX",
    "entity": "RR Ltd",
    "company": "RR Ltd",
    "desc": null,
    "sector": null,
    "type": "Structured Credit",
    "affil": "",
    "fv": 980.0,
    "cost": 999.0,
    "par": null,
    "mark": 98.1,
    "spread": 4.7,
    "rate": 8.37,
    "baseRate": "SOFR",
    "maturity": "2040-04",
    "acq": null,
    "ccy": "USD",
    "pik": false
  },
  {
    "bdc": "TSLX",
    "entity": "Texas Debt Capital CLO Ltd",
    "company": "Texas Debt Capital CLO Ltd",
    "desc": null,
    "sector": null,
    "type": "Structured Credit",
    "affil": "",
    "fv": 1973.0,
    "cost": 2023.0,
    "par": null,
    "mark": 97.53,
    "spread": 4.95,
    "rate": 8.62,
    "baseRate": "SOFR",
    "maturity": "2038-07",
    "acq": null,
    "ccy": "USD",
    "pik": false
  },
  {
    "bdc": "TSLX",
    "entity": "Whitebox CLO Ltd",
    "company": "Whitebox CLO Ltd",
    "desc": null,
    "sector": null,
    "type": "Structured Credit",
    "affil": "",
    "fv": 1491.0,
    "cost": 1528.0,
    "par": null,
    "mark": 97.58,
    "spread": 6.48,
    "rate": 10.15,
    "baseRate": "SOFR",
    "maturity": "2036-04",
    "acq": null,
    "ccy": "USD",
    "pik": false
  },
  {
    "bdc": "TSLX",
    "entity": "Structured Credit Partners JV, LLC",
    "company": "Structured Credit Partners JV, LLC",
    "desc": null,
    "sector": null,
    "type": "",
    "affil": "",
    "fv": 14665.0,
    "cost": null,
    "par": null,
    "mark": null,
    "spread": null,
    "rate": null,
    "baseRate": null,
    "maturity": null,
    "acq": null,
    "ccy": "USD",
    "pik": false
  },
  {
    "bdc": "TSLX",
    "entity": "IRGSE Holding Corp",
    "company": "IRGSE Holding Corp",
    "desc": null,
    "sector": null,
    "type": "",
    "affil": "",
    "fv": 58505.0,
    "cost": null,
    "par": null,
    "mark": null,
    "spread": null,
    "rate": null,
    "baseRate": null,
    "maturity": null,
    "acq": null,
    "ccy": "USD",
    "pik": false
  }
]